<?xml version="1.0" encoding="UTF-8"?>
<PARAMETER>
  <单动速度>
    <高速速度>5000</高速速度>
    <低速速度>30</低速速度>
    <加减速度>5000</加减速度>
  </单动速度>
  <其他>
    <打胶速度>10</打胶速度>
    <打胶半径>10</打胶半径>
    <UV光时间>3.5</UV光时间>
    <夹爪延时>3</夹爪延时>
    <屏蔽打胶>true</屏蔽打胶>
    <屏蔽UV光>true</屏蔽UV光>
    <屏蔽相机报警>false</屏蔽相机报警>
    <Z轴抬升高度>20</Z轴抬升高度>
    <判断延时>2</判断延时>
    <预留选项>0</预留选项>
    <取产品方式>0</取产品方式>
    <打胶对位补偿>0</打胶对位补偿>
    <力传感器量程>100</力传感器量程>
    <打胶补正基准X>0</打胶补正基准X>
    <打胶补正基准Y>0</打胶补正基准Y>
    <打胶补偿角>5</打胶补偿角>
    <取料方向>1</取料方向>
  </其他>
  <自动转角>
    <零件编号>0</零件编号>
    <列1>0</列1>
    <列2>0</列2>
    <列3>90</列3>
    <列4>90</列4>
    <列5>180</列5>
    <列6>180</列6>
    <列7>270</列7>
    <列8>270</列8>
    <列9>0</列9>
    <列10>0</列10>
    <列11>0</列11>
    <列12>0</列12>
    <列13>0</列13>
    <列14>0</列14>
    <列15>0</列15>
    <列16>0</列16>
    <列17>0</列17>
    <列18>0</列18>
    <列19>0</列19>
    <列20>0</列20>
    <列21>0</列21>
    <列22>0</列22>
    <列23>0</列23>
    <列24>0</列24>
    <列25>0</列25>
    <列26>0</列26>
    <列27>0</列27>
    <列28>0</列28>
    <列29>0</列29>
    <列30>0</列30>
  </自动转角>
  <屏蔽信息>
    <急停>false</急停>
    <启动>false</启动>
    <复位>false</复位>
    <暂停>false</暂停>
    <正压>false</正压>
    <负压1>false</负压1>
    <负压2>false</负压2>
    <负压3>false</负压3>
    <打胶气缸上>false</打胶气缸上>
    <打胶气缸下>false</打胶气缸下>
    <夹爪气缸上>false</夹爪气缸上>
    <夹爪气缸下>false</夹爪气缸下>
    <光幕>false</光幕>
    <快换负压>false</快换负压>
    <转台负压>true</转台负压>
    <预留1>false</预留1>
    <预留2>false</预留2>
    <预留3>false</预留3>
    <预留4>false</预留4>
    <预留5>false</预留5>
    <力控>false</力控>
    <拍照>false</拍照>
  </屏蔽信息>
  <料盘>
    <列数>12</列数>
    <零件数>12</零件数>
    <列间隔>8</列间隔>
  </料盘>
  <夹具盘>
    <列数>5</列数>
    <行数>4</行数>
    <列间隔>50</列间隔>
    <行间隔>110</行间隔>
  </夹具盘>
  <吸零件_P0>
    <PositionYY>141.9995</PositionYY>
    <PositionY>0.0275</PositionY>
    <PositionTHETA>0.0000</PositionTHETA>
    <PositionX>-30.1084</PositionX>
    <PositionZ>45.1260</PositionZ>
  </吸零件_P0>
  <换夹具_P1>
    <PositionYY>-110.0305</PositionYY>
    <PositionY>0.0275</PositionY>
    <PositionTHETA>0.0000</PositionTHETA>
    <PositionX>-238.0484</PositionX>
    <PositionZ>84.2243</PositionZ>
  </换夹具_P1>
  <拍照1_P2>
    <PositionYY>141.6409</PositionYY>
    <PositionY>0.0296</PositionY>
    <PositionTHETA>0.0000</PositionTHETA>
    <PositionX>-30.5838</PositionX>
    <PositionZ>45.2200</PositionZ>
  </拍照1_P2>
  <拍照2_P3>
    <PositionYY>144.0819</PositionYY>
    <PositionY>0.0296</PositionY>
    <PositionTHETA>0.0000</PositionTHETA>
    <PositionX>19.9854</PositionX>
    <PositionZ>43.5908</PositionZ>
  </拍照2_P3>
  <拍照3_P4>
    <PositionYY>144.0819</PositionYY>
    <PositionY>-20.9704</PositionY>
    <PositionTHETA>0.0000</PositionTHETA>
    <PositionX>133.5254</PositionX>
    <PositionZ>44.7509</PositionZ>
  </拍照3_P4>
  <拍照4_P5>
    <PositionYY>144.0819</PositionYY>
    <PositionY>-19.3704</PositionY>
    <PositionTHETA>0.0000</PositionTHETA>
    <PositionX>143.6854</PositionX>
    <PositionZ>49.6909</PositionZ>
  </拍照4_P5>
  <打胶_P6>
    <PositionYY>123.4409</PositionYY>
    <PositionY>0.0296</PositionY>
    <PositionTHETA>0.0000</PositionTHETA>
    <PositionX>90.2962</PositionX>
    <PositionZ>20.5499</PositionZ>
  </打胶_P6>
  <吸笔取_P7>
    <PositionYY>123.4409</PositionYY>
    <PositionY>0.0296</PositionY>
    <PositionTHETA>0.0000</PositionTHETA>
    <PositionX>149.6962</PositionX>
    <PositionZ>44.6401</PositionZ>
  </吸笔取_P7>
  <UV光_P8>
    <PositionYY>123.4409</PositionYY>
    <PositionY>0.0296</PositionY>
    <PositionTHETA>0.0000</PositionTHETA>
    <PositionX>63.4162</PositionX>
    <PositionZ>54.4799</PositionZ>
  </UV光_P8>
  <夹爪取_P9>
    <PositionYY>123.4409</PositionYY>
    <PositionY>0.0296</PositionY>
    <PositionTHETA>0.0000</PositionTHETA>
    <PositionX>35.9662</PositionX>
    <PositionZ>54.4799</PositionZ>
  </夹爪取_P9>
  <夹爪放_P10>
    <PositionYY>105.9600</PositionYY>
    <PositionY>0.0000</PositionY>
    <PositionTHETA>0.0000</PositionTHETA>
    <PositionX>-129.7200</PositionX>
    <PositionZ>40.1101</PositionZ>
  </夹爪放_P10>
  <吸笔放_P11>
    <PositionYY>105.9600</PositionYY>
    <PositionY>0.0000</PositionY>
    <PositionTHETA>0.0000</PositionTHETA>
    <PositionX>-19.4700</PositionX>
    <PositionZ>46.5901</PositionZ>
  </吸笔放_P11>
  <短距组装_V0>
    <YY_V>1000</YY_V>
    <Y_V>1200</Y_V>
    <THETA_V>6000</THETA_V>
    <X_V>3000</X_V>
    <Z_V>1200</Z_V>
    <YY_A>2000</YY_A>
    <Y_A>5000</Y_A>
    <THETA_A>1000</THETA_A>
    <X_A>5000</X_A>
    <Z_AUP>3000</Z_AUP>
    <Z_ADOWN>3000</Z_ADOWN>
  </短距组装_V0>
  <放夹具_V1>
    <YY_V>1200</YY_V>
    <Y_V>1200</Y_V>
    <THETA_V>6000</THETA_V>
    <X_V>3000</X_V>
    <Z_V>1200</Z_V>
    <YY_A>5000</YY_A>
    <Y_A>5000</Y_A>
    <THETA_A>1000</THETA_A>
    <X_A>5000</X_A>
    <Z_AUP>3000</Z_AUP>
    <Z_ADOWN>3000</Z_ADOWN>
  </放夹具_V1>
  <取夹具_V2>
    <YY_V>1000</YY_V>
    <Y_V>1000</Y_V>
    <THETA_V>6000</THETA_V>
    <X_V>1000</X_V>
    <Z_V>1000</Z_V>
    <YY_A>5000</YY_A>
    <Y_A>5000</Y_A>
    <THETA_A>1000</THETA_A>
    <X_A>5000</X_A>
    <Z_AUP>700</Z_AUP>
    <Z_ADOWN>700</Z_ADOWN>
  </取夹具_V2>
  <拍照1_V3>
    <YY_V>1200</YY_V>
    <Y_V>1200</Y_V>
    <THETA_V>6000</THETA_V>
    <X_V>3000</X_V>
    <Z_V>1200</Z_V>
    <YY_A>5000</YY_A>
    <Y_A>5000</Y_A>
    <THETA_A>1000</THETA_A>
    <X_A>5000</X_A>
    <Z_AUP>3000</Z_AUP>
    <Z_ADOWN>3000</Z_ADOWN>
  </拍照1_V3>
  <拍照3_V4>
    <YY_V>1200</YY_V>
    <Y_V>1200</Y_V>
    <THETA_V>6000</THETA_V>
    <X_V>3000</X_V>
    <Z_V>1200</Z_V>
    <YY_A>5000</YY_A>
    <Y_A>5000</Y_A>
    <THETA_A>1000</THETA_A>
    <X_A>5000</X_A>
    <Z_AUP>3000</Z_AUP>
    <Z_ADOWN>3000</Z_ADOWN>
  </拍照3_V4>
  <拍照2_V5>
    <YY_V>1200</YY_V>
    <Y_V>1200</Y_V>
    <THETA_V>6000</THETA_V>
    <X_V>3000</X_V>
    <Z_V>1200</Z_V>
    <YY_A>5000</YY_A>
    <Y_A>5000</Y_A>
    <THETA_A>1000</THETA_A>
    <X_A>5000</X_A>
    <Z_AUP>3000</Z_AUP>
    <Z_ADOWN>3000</Z_ADOWN>
  </拍照2_V5>
  <吸取零件_V6>
    <YY_V>1200</YY_V>
    <Y_V>1200</Y_V>
    <THETA_V>6000</THETA_V>
    <X_V>3000</X_V>
    <Z_V>1200</Z_V>
    <YY_A>5000</YY_A>
    <Y_A>5000</Y_A>
    <THETA_A>1000</THETA_A>
    <X_A>5000</X_A>
    <Z_AUP>3000</Z_AUP>
    <Z_ADOWN>3000</Z_ADOWN>
  </吸取零件_V6>
  <产品打胶_V7>
    <YY_V>1200</YY_V>
    <Y_V>1200</Y_V>
    <THETA_V>6000</THETA_V>
    <X_V>3000</X_V>
    <Z_V>1200</Z_V>
    <YY_A>5000</YY_A>
    <Y_A>5000</Y_A>
    <THETA_A>1000</THETA_A>
    <X_A>5000</X_A>
    <Z_AUP>3000</Z_AUP>
    <Z_ADOWN>3000</Z_ADOWN>
  </产品打胶_V7>
  <UV固化_V8>
    <YY_V>1200</YY_V>
    <Y_V>1200</Y_V>
    <THETA_V>6000</THETA_V>
    <X_V>3000</X_V>
    <Z_V>1200</Z_V>
    <YY_A>5000</YY_A>
    <Y_A>5000</Y_A>
    <THETA_A>1000</THETA_A>
    <X_A>5000</X_A>
    <Z_AUP>3000</Z_AUP>
    <Z_ADOWN>3000</Z_ADOWN>
  </UV固化_V8>
  <取产品_V9>
    <YY_V>1200</YY_V>
    <Y_V>1200</Y_V>
    <THETA_V>6000</THETA_V>
    <X_V>3000</X_V>
    <Z_V>1200</Z_V>
    <YY_A>5000</YY_A>
    <Y_A>5000</Y_A>
    <THETA_A>1000</THETA_A>
    <X_A>5000</X_A>
    <Z_AUP>3000</Z_AUP>
    <Z_ADOWN>3000</Z_ADOWN>
  </取产品_V9>
  <放产品_V10>
    <YY_V>1200</YY_V>
    <Y_V>1200</Y_V>
    <THETA_V>6000</THETA_V>
    <X_V>3000</X_V>
    <Z_V>1200</Z_V>
    <YY_A>5000</YY_A>
    <Y_A>5000</Y_A>
    <THETA_A>1000</THETA_A>
    <X_A>5000</X_A>
    <Z_AUP>3000</Z_AUP>
    <Z_ADOWN>3000</Z_ADOWN>
  </放产品_V10>
  <长距组装_V11>
    <YY_V>1200</YY_V>
    <Y_V>1200</Y_V>
    <THETA_V>6000</THETA_V>
    <X_V>3000</X_V>
    <Z_V>1200</Z_V>
    <YY_A>5000</YY_A>
    <Y_A>5000</Y_A>
    <THETA_A>1000</THETA_A>
    <X_A>5000</X_A>
    <Z_AUP>3000</Z_AUP>
    <Z_ADOWN>3000</Z_ADOWN>
  </长距组装_V11>
  <拍照4_V12>
    <YY_V>1200</YY_V>
    <Y_V>1200</Y_V>
    <THETA_V>6000</THETA_V>
    <X_V>3000</X_V>
    <Z_V>1200</Z_V>
    <YY_A>5000</YY_A>
    <Y_A>5000</Y_A>
    <THETA_A>1000</THETA_A>
    <X_A>5000</X_A>
    <Z_AUP>3000</Z_AUP>
    <Z_ADOWN>3000</Z_ADOWN>
  </拍照4_V12>
  <零件名>
    <零件0>Barrel</零件0>
    <零件1>P1</零件1>
    <零件2>S1</零件2>
    <零件3>P2</零件3>
    <零件4>S2</零件4>
    <零件5>P3</零件5>
    <零件6>S3</零件6>
    <零件7>P4</零件7>
    <零件8>S4</零件8>
    <零件9>S5</零件9>
    <零件10>P5</零件10>
    <零件11>ST</零件11>
    <零件12>8</零件12>
    <零件13>8</零件13>
    <零件14>8</零件14>
    <零件15>8</零件15>
    <零件16>8</零件16>
    <零件17>8</零件17>
    <零件18>8</零件18>
    <零件19>8</零件19>
    <零件20>0</零件20>
    <零件21>8</零件21>
    <零件22>8</零件22>
    <零件23>8</零件23>
    <零件24>8</零件24>
    <零件25>8</零件25>
    <零件26>8</零件26>
    <零件27>8</零件27>
    <零件28>8</零件28>
    <零件29>8</零件29>
  </零件名>
  <夹具号>
    <零件0>0</零件0>
    <零件1>1</零件1>
    <零件2>2</零件2>
    <零件3>1</零件3>
    <零件4>3</零件4>
    <零件5>1</零件5>
    <零件6>4</零件6>
    <零件7>5</零件7>
    <零件8>6</零件8>
    <零件9>7</零件9>
    <零件10>8</零件10>
    <零件11>9</零件11>
    <零件12>8</零件12>
    <零件13>8</零件13>
    <零件14>8</零件14>
    <零件15>8</零件15>
    <零件16>8</零件16>
    <零件17>8</零件17>
    <零件18>8</零件18>
    <零件19>8</零件19>
    <零件20>0</零件20>
    <零件21>8</零件21>
    <零件22>8</零件22>
    <零件23>8</零件23>
    <零件24>8</零件24>
    <零件25>8</零件25>
    <零件26>8</零件26>
    <零件27>8</零件27>
    <零件28>8</零件28>
    <零件29>8</零件29>
  </夹具号>
  <零件间隔>
    <零件0>0</零件0>
    <零件1>12</零件1>
    <零件2>8</零件2>
    <零件3>8</零件3>
    <零件4>8</零件4>
    <零件5>8</零件5>
    <零件6>8</零件6>
    <零件7>8</零件7>
    <零件8>8</零件8>
    <零件9>8</零件9>
    <零件10>8</零件10>
    <零件11>8</零件11>
    <零件12>8</零件12>
    <零件13>8</零件13>
    <零件14>8</零件14>
    <零件15>8</零件15>
    <零件16>8</零件16>
    <零件17>8</零件17>
    <零件18>8</零件18>
    <零件19>8</零件19>
    <零件20>0</零件20>
    <零件21>8</零件21>
    <零件22>8</零件22>
    <零件23>8</零件23>
    <零件24>8</零件24>
    <零件25>8</零件25>
    <零件26>8</零件26>
    <零件27>8</零件27>
    <零件28>8</零件28>
    <零件29>8</零件29>
  </零件间隔>
  <焦距补偿3>
    <零件0>0</零件0>
    <零件1>0</零件1>
    <零件2>0</零件2>
    <零件3>0</零件3>
    <零件4>0</零件4>
    <零件5>0</零件5>
    <零件6>0</零件6>
    <零件7>0</零件7>
    <零件8>0</零件8>
    <零件9>0</零件9>
    <零件10>0</零件10>
    <零件11>0</零件11>
    <零件12>0</零件12>
    <零件13>0</零件13>
    <零件14>0</零件14>
    <零件15>0</零件15>
    <零件16>0</零件16>
    <零件17>0</零件17>
    <零件18>0</零件18>
    <零件19>0</零件19>
    <零件20>0</零件20>
    <零件21>0</零件21>
    <零件22>0</零件22>
    <零件23>0</零件23>
    <零件24>0</零件24>
    <零件25>0</零件25>
    <零件26>0</零件26>
    <零件27>0</零件27>
    <零件28>0</零件28>
    <零件29>0</零件29>
  </焦距补偿3>
  <吸笔校正X>
    <零件0>0</零件0>
    <零件1>-0.3500</零件1>
    <零件2>-0.3600</零件2>
    <零件3>-0.3000</零件3>
    <零件4>-0.3500</零件4>
    <零件5>-0.3000</零件5>
    <零件6>-0.3500</零件6>
    <零件7>-0.3500</零件7>
    <零件8>-0.3500</零件8>
    <零件9>-0.4500</零件9>
    <零件10>-0.2500</零件10>
    <零件11>-0.3000</零件11>
    <零件12>0</零件12>
    <零件13>0</零件13>
    <零件14>0</零件14>
    <零件15>0</零件15>
    <零件16>0</零件16>
    <零件17>0</零件17>
    <零件18>0</零件18>
    <零件19>0</零件19>
    <零件20>0</零件20>
    <零件21>0</零件21>
    <零件22>0</零件22>
    <零件23>0</零件23>
    <零件24>0</零件24>
    <零件25>0</零件25>
    <零件26>0</零件26>
    <零件27>0</零件27>
    <零件28>0</零件28>
    <零件29>0</零件29>
  </吸笔校正X>
  <吸笔校正YY>
    <零件0>0</零件0>
    <零件1>0.2500</零件1>
    <零件2>0.0500</零件2>
    <零件3>0.1500</零件3>
    <零件4>0.2000</零件4>
    <零件5>0.3000</零件5>
    <零件6>0.2500</零件6>
    <零件7>0.3000</零件7>
    <零件8>0.3000</零件8>
    <零件9>0.3500</零件9>
    <零件10>0.2500</零件10>
    <零件11>0.3500</零件11>
    <零件12>0</零件12>
    <零件13>0</零件13>
    <零件14>0</零件14>
    <零件15>0</零件15>
    <零件16>0</零件16>
    <零件17>0</零件17>
    <零件18>0</零件18>
    <零件19>0</零件19>
    <零件20>0</零件20>
    <零件21>0</零件21>
    <零件22>0</零件22>
    <零件23>0</零件23>
    <零件24>0</零件24>
    <零件25>0</零件25>
    <零件26>0</零件26>
    <零件27>0</零件27>
    <零件28>0</零件28>
    <零件29>0</零件29>
  </吸笔校正YY>
  <拍照配置>
    <零件0>2</零件0>
    <零件1>431</零件1>
    <零件2>43</零件2>
    <零件3>431</零件3>
    <零件4>43</零件4>
    <零件5>431</零件5>
    <零件6>43</零件6>
    <零件7>431</零件7>
    <零件8>431</零件8>
    <零件9>43</零件9>
    <零件10>431</零件10>
    <零件11>431</零件11>
    <零件12>4321</零件12>
    <零件13>4321</零件13>
    <零件14>4321</零件14>
    <零件15>4321</零件15>
    <零件16>4321</零件16>
    <零件17>4321</零件17>
    <零件18>4321</零件18>
    <零件19>4321</零件19>
    <零件20>4321</零件20>
    <零件21>4321</零件21>
    <零件22>4321</零件22>
    <零件23>4321</零件23>
    <零件24>4321</零件24>
    <零件25>4321</零件25>
    <零件26>4321</零件26>
    <零件27>4321</零件27>
    <零件28>4321</零件28>
    <零件29>4321</零件29>
  </拍照配置>
  <角度偏移量>
    <零件0>0</零件0>
    <零件1>90</零件1>
    <零件2>0</零件2>
    <零件3>90</零件3>
    <零件4>0</零件4>
    <零件5>0</零件5>
    <零件6>0</零件6>
    <零件7>0</零件7>
    <零件8>0</零件8>
    <零件9>0</零件9>
    <零件10>0</零件10>
    <零件11>0</零件11>
    <零件12>0</零件12>
    <零件13>0</零件13>
    <零件14>0</零件14>
    <零件15>0</零件15>
    <零件16>0</零件16>
    <零件17>0</零件17>
    <零件18>0</零件18>
    <零件19>0</零件19>
    <零件20>0</零件20>
    <零件21>0</零件21>
    <零件22>0</零件22>
    <零件23>0</零件23>
    <零件24>0</零件24>
    <零件25>0</零件25>
    <零件26>0</零件26>
    <零件27>0</零件27>
    <零件28>0</零件28>
    <零件29>0</零件29>
  </角度偏移量>
  <屏蔽判断>
    <零件0>false</零件0>
    <零件1>false</零件1>
    <零件2>false</零件2>
    <零件3>false</零件3>
    <零件4>false</零件4>
    <零件5>false</零件5>
    <零件6>false</零件6>
    <零件7>false</零件7>
    <零件8>false</零件8>
    <零件9>false</零件9>
    <零件10>false</零件10>
    <零件11>false</零件11>
    <零件12>false</零件12>
    <零件13>false</零件13>
    <零件14>false</零件14>
    <零件15>false</零件15>
    <零件16>false</零件16>
    <零件17>false</零件17>
    <零件18>false</零件18>
    <零件19>false</零件19>
    <零件20>false</零件20>
    <零件21>false</零件21>
    <零件22>false</零件22>
    <零件23>false</零件23>
    <零件24>false</零件24>
    <零件25>false</零件25>
    <零件26>false</零件26>
    <零件27>false</零件27>
    <零件28>false</零件28>
    <零件29>false</零件29>
  </屏蔽判断>
  <力控使能>
    <零件0>false</零件0>
    <零件1>true</零件1>
    <零件2>true</零件2>
    <零件3>true</零件3>
    <零件4>true</零件4>
    <零件5>true</零件5>
    <零件6>true</零件6>
    <零件7>true</零件7>
    <零件8>true</零件8>
    <零件9>true</零件9>
    <零件10>true</零件10>
    <零件11>true</零件11>
    <零件12>false</零件12>
    <零件13>false</零件13>
    <零件14>false</零件14>
    <零件15>false</零件15>
    <零件16>false</零件16>
    <零件17>false</零件17>
    <零件18>false</零件18>
    <零件19>false</零件19>
    <零件20>false</零件20>
    <零件21>false</零件21>
    <零件22>false</零件22>
    <零件23>false</零件23>
    <零件24>false</零件24>
    <零件25>false</零件25>
    <零件26>false</零件26>
    <零件27>false</零件27>
    <零件28>false</零件28>
    <零件29>false</零件29>
  </力控使能>
  <吸零件Z轴补偿>
    <零件0>4.4998</零件0>
    <零件1>2.1001</零件1>
    <零件2>2.4000</零件2>
    <零件3>2.1001</零件3>
    <零件4>2.2999</零件4>
    <零件5>2.0000</零件5>
    <零件6>2.2498</零件6>
    <零件7>2.0501</零件7>
    <零件8>1.8998</零件8>
    <零件9>2.2498</零件9>
    <零件10>2.2498</零件10>
    <零件11>1.6002</零件11>
    <零件12>0</零件12>
    <零件13>0</零件13>
    <零件14>0</零件14>
    <零件15>0</零件15>
    <零件16>0</零件16>
    <零件17>0</零件17>
    <零件18>0</零件18>
    <零件19>0</零件19>
    <零件20>0</零件20>
    <零件21>0</零件21>
    <零件22>0</零件22>
    <零件23>0</零件23>
    <零件24>0</零件24>
    <零件25>0</零件25>
    <零件26>0</零件26>
    <零件27>0</零件27>
    <零件28>0</零件28>
    <零件29>0</零件29>
  </吸零件Z轴补偿>
  <装零件Z轴补偿>
    <零件0>1.7001</零件0>
    <零件1>1.1</零件1>
    <零件2>0</零件2>
    <零件3>0</零件3>
    <零件4>0</零件4>
    <零件5>0</零件5>
    <零件6>0</零件6>
    <零件7>0</零件7>
    <零件8>0</零件8>
    <零件9>0</零件9>
    <零件10>0</零件10>
    <零件11>0</零件11>
    <零件12>0</零件12>
    <零件13>0</零件13>
    <零件14>0</零件14>
    <零件15>0</零件15>
    <零件16>0</零件16>
    <零件17>0</零件17>
    <零件18>0</零件18>
    <零件19>0</零件19>
    <零件20>0</零件20>
    <零件21>0</零件21>
    <零件22>0</零件22>
    <零件23>0</零件23>
    <零件24>0</零件24>
    <零件25>0</零件25>
    <零件26>0</零件26>
    <零件27>0</零件27>
    <零件28>0</零件28>
    <零件29>0</零件29>
  </装零件Z轴补偿>
  <压力值>
    <零件0>0</零件0>
    <零件1>20</零件1>
    <零件2>1</零件2>
    <零件3>20</零件3>
    <零件4>1</零件4>
    <零件5>20</零件5>
    <零件6>1</零件6>
    <零件7>20</零件7>
    <零件8>20</零件8>
    <零件9>1</零件9>
    <零件10>20</零件10>
    <零件11>20</零件11>
    <零件12>0</零件12>
    <零件13>0</零件13>
    <零件14>0</零件14>
    <零件15>0</零件15>
    <零件16>0</零件16>
    <零件17>0</零件17>
    <零件18>0</零件18>
    <零件19>0</零件19>
    <零件20>0</零件20>
    <零件21>0</零件21>
    <零件22>0</零件22>
    <零件23>0</零件23>
    <零件24>0</零件24>
    <零件25>0</零件25>
    <零件26>0</零件26>
    <零件27>0</零件27>
    <零件28>0</零件28>
    <零件29>0</零件29>
  </压力值>
  <压力误差限>
    <零件0>0.5</零件0>
    <零件1>0.5</零件1>
    <零件2>0.5</零件2>
    <零件3>0.5</零件3>
    <零件4>0.5</零件4>
    <零件5>0.5</零件5>
    <零件6>0.5</零件6>
    <零件7>0.5</零件7>
    <零件8>0.5</零件8>
    <零件9>0.5</零件9>
    <零件10>0.5</零件10>
    <零件11>0.5</零件11>
    <零件12>0</零件12>
    <零件13>0</零件13>
    <零件14>0</零件14>
    <零件15>0</零件15>
    <零件16>0</零件16>
    <零件17>0</零件17>
    <零件18>0</零件18>
    <零件19>0</零件19>
    <零件20>0</零件20>
    <零件21>0</零件21>
    <零件22>0</零件22>
    <零件23>0</零件23>
    <零件24>0</零件24>
    <零件25>0</零件25>
    <零件26>0</零件26>
    <零件27>0</零件27>
    <零件28>0</零件28>
    <零件29>0</零件29>
  </压力误差限>
  <压力保持时间>
    <零件0>0.1</零件0>
    <零件1>0.1</零件1>
    <零件2>0.1</零件2>
    <零件3>0.1</零件3>
    <零件4>0.1</零件4>
    <零件5>0.1</零件5>
    <零件6>0.1</零件6>
    <零件7>0.1</零件7>
    <零件8>0.1</零件8>
    <零件9>0.1</零件9>
    <零件10>0.1</零件10>
    <零件11>0.1</零件11>
    <零件12>0</零件12>
    <零件13>0</零件13>
    <零件14>0</零件14>
    <零件15>0</零件15>
    <零件16>0</零件16>
    <零件17>0</零件17>
    <零件18>0</零件18>
    <零件19>0</零件19>
    <零件20>0</零件20>
    <零件21>0</零件21>
    <零件22>0</零件22>
    <零件23>0</零件23>
    <零件24>0</零件24>
    <零件25>0</零件25>
    <零件26>0</零件26>
    <零件27>0</零件27>
    <零件28>0</零件28>
    <零件29>0</零件29>
  </压力保持时间>
  <压力步进量>
    <零件0>0.1</零件0>
    <零件1>0.1</零件1>
    <零件2>0.1</零件2>
    <零件3>0.1</零件3>
    <零件4>0.1</零件4>
    <零件5>0.1</零件5>
    <零件6>0.1</零件6>
    <零件7>0.1</零件7>
    <零件8>0.1</零件8>
    <零件9>0.1</零件9>
    <零件10>0.1</零件10>
    <零件11>0.1</零件11>
    <零件12>0</零件12>
    <零件13>0</零件13>
    <零件14>0</零件14>
    <零件15>0</零件15>
    <零件16>0</零件16>
    <零件17>0</零件17>
    <零件18>0</零件18>
    <零件19>0</零件19>
    <零件20>0</零件20>
    <零件21>0</零件21>
    <零件22>0</零件22>
    <零件23>0</零件23>
    <零件24>0</零件24>
    <零件25>0</零件25>
    <零件26>0</零件26>
    <零件27>0</零件27>
    <零件28>0</零件28>
    <零件29>0</零件29>
  </压力步进量>
  <压力速度>
    <零件0>100</零件0>
    <零件1>100</零件1>
    <零件2>100</零件2>
    <零件3>100</零件3>
    <零件4>100</零件4>
    <零件5>100</零件5>
    <零件6>100</零件6>
    <零件7>100</零件7>
    <零件8>100</零件8>
    <零件9>100</零件9>
    <零件10>100</零件10>
    <零件11>100</零件11>
    <零件12>0</零件12>
    <零件13>0</零件13>
    <零件14>0</零件14>
    <零件15>0</零件15>
    <零件16>0</零件16>
    <零件17>0</零件17>
    <零件18>0</零件18>
    <零件19>0</零件19>
    <零件20>0</零件20>
    <零件21>0</零件21>
    <零件22>0</零件22>
    <零件23>0</零件23>
    <零件24>0</零件24>
    <零件25>0</零件25>
    <零件26>0</零件26>
    <零件27>0</零件27>
    <零件28>0</零件28>
    <零件29>0</零件29>
  </压力速度>
  <负压表配置>
    <零件0>1</零件0>
    <零件1>3</零件1>
    <零件2>2</零件2>
    <零件3>2</零件3>
    <零件4>2</零件4>
    <零件5>3</零件5>
    <零件6>2</零件6>
    <零件7>3</零件7>
    <零件8>1</零件8>
    <零件9>3</零件9>
    <零件10>2</零件10>
    <零件11>1</零件11>
    <零件12>1</零件12>
    <零件13>1</零件13>
    <零件14>1</零件14>
    <零件15>1</零件15>
    <零件16>1</零件16>
    <零件17>1</零件17>
    <零件18>1</零件18>
    <零件19>1</零件19>
    <零件20>1</零件20>
    <零件21>1</零件21>
    <零件22>1</零件22>
    <零件23>1</零件23>
    <零件24>1</零件24>
    <零件25>1</零件25>
    <零件26>1</零件26>
    <零件27>1</零件27>
    <零件28>1</零件28>
    <零件29>1</零件29>
  </负压表配置>
  <焦距补偿2>
    <零件0>6.0822406098282E-06</零件0>
    <零件1>0</零件1>
    <零件2>0</零件2>
    <零件3>0</零件3>
    <零件4>0</零件4>
    <零件5>0</零件5>
    <零件6>0</零件6>
    <零件7>0</零件7>
    <零件8>0</零件8>
    <零件9>0</零件9>
    <零件10>0</零件10>
    <零件11>0</零件11>
    <零件12>0</零件12>
    <零件13>0</零件13>
    <零件14>0</零件14>
    <零件15>0</零件15>
    <零件16>0</零件16>
    <零件17>0</零件17>
    <零件18>0</零件18>
    <零件19>0</零件19>
    <零件20>0</零件20>
    <零件21>0</零件21>
    <零件22>0</零件22>
    <零件23>0</零件23>
    <零件24>0</零件24>
    <零件25>0</零件25>
    <零件26>0</零件26>
    <零件27>0</零件27>
    <零件28>0</零件28>
    <零件29>0</零件29>
  </焦距补偿2>
  <焦距补偿1>
    <零件0>0</零件0>
    <零件1>4.13065143799298</零件1>
    <零件2>0</零件2>
    <零件3>0</零件3>
    <零件4>0</零件4>
    <零件5>0</零件5>
    <零件6>0</零件6>
    <零件7>0</零件7>
    <零件8>0</零件8>
    <零件9>0</零件9>
    <零件10>0</零件10>
    <零件11>0</零件11>
    <零件12>0</零件12>
    <零件13>0</零件13>
    <零件14>0</零件14>
    <零件15>0</零件15>
    <零件16>0</零件16>
    <零件17>0</零件17>
    <零件18>0</零件18>
    <零件19>0</零件19>
    <零件20>0</零件20>
    <零件21>0</零件21>
    <零件22>0</零件22>
    <零件23>0</零件23>
    <零件24>0</零件24>
    <零件25>0</零件25>
    <零件26>0</零件26>
    <零件27>0</零件27>
    <零件28>0</零件28>
    <零件29>0</零件29>
  </焦距补偿1>
  <焦距补偿4>
    <零件0>1.69978634</零件0>
    <零件1>-4.85620070236337E-05</零件1>
    <零件2>0.399725960715685</零件2>
    <零件3>1.50017397887122</零件3>
    <零件4>-0.500177320984399</零件4>
    <零件5>-0.500177320984399</零件5>
    <零件6>-0.900413320984406</零件6>
    <零件7>-1.00034727632815</零件7>
    <零件8>0.200011278592974</零件8>
    <零件9>1.69978634</零件9>
    <零件10>-0.400243320984401</零件10>
    <零件11>-0.20010752140702</零件11>
    <零件12>0</零件12>
    <零件13>0</零件13>
    <零件14>0</零件14>
    <零件15>0</零件15>
    <零件16>0</零件16>
    <零件17>0</零件17>
    <零件18>0</零件18>
    <零件19>0</零件19>
    <零件20>0</零件20>
    <零件21>0</零件21>
    <零件22>0</零件22>
    <零件23>0</零件23>
    <零件24>0</零件24>
    <零件25>0</零件25>
    <零件26>0</零件26>
    <零件27>0</零件27>
    <零件28>0</零件28>
    <零件29>0</零件29>
  </焦距补偿4>
  <生产日期>
    <零件0>0</零件0>
    <零件1>0</零件1>
    <零件2>0</零件2>
    <零件3>0</零件3>
    <零件4>0</零件4>
    <零件5>0</零件5>
    <零件6>0</零件6>
    <零件7>0</零件7>
    <零件8>0</零件8>
    <零件9>0</零件9>
    <零件10>0</零件10>
    <零件11>0</零件11>
    <零件12>0</零件12>
    <零件13>0</零件13>
    <零件14>0</零件14>
    <零件15>0</零件15>
    <零件16>0</零件16>
    <零件17>0</零件17>
    <零件18>0</零件18>
    <零件19>0</零件19>
    <零件20>0</零件20>
    <零件21>0</零件21>
    <零件22>0</零件22>
    <零件23>0</零件23>
    <零件24>0</零件24>
    <零件25>0</零件25>
    <零件26>0</零件26>
    <零件27>0</零件27>
    <零件28>0</零件28>
    <零件29>0</零件29>
  </生产日期>
  <模具号>
    <零件0>0</零件0>
    <零件1>0</零件1>
    <零件2>0</零件2>
    <零件3>0</零件3>
    <零件4>0</零件4>
    <零件5>0</零件5>
    <零件6>0</零件6>
    <零件7>0</零件7>
    <零件8>0</零件8>
    <零件9>0</零件9>
    <零件10>0</零件10>
    <零件11>0</零件11>
    <零件12>0</零件12>
    <零件13>0</零件13>
    <零件14>0</零件14>
    <零件15>0</零件15>
    <零件16>0</零件16>
    <零件17>0</零件17>
    <零件18>0</零件18>
    <零件19>0</零件19>
    <零件20>0</零件20>
    <零件21>0</零件21>
    <零件22>0</零件22>
    <零件23>0</零件23>
    <零件24>0</零件24>
    <零件25>0</零件25>
    <零件26>0</零件26>
    <零件27>0</零件27>
    <零件28>0</零件28>
    <零件29>0</零件29>
  </模具号>
  <穴号>
    <零件0>0</零件0>
    <零件1>0</零件1>
    <零件2>0</零件2>
    <零件3>0</零件3>
    <零件4>0</零件4>
    <零件5>0</零件5>
    <零件6>0</零件6>
    <零件7>0</零件7>
    <零件8>0</零件8>
    <零件9>0</零件9>
    <零件10>0</零件10>
    <零件11>0</零件11>
    <零件12>0</零件12>
    <零件13>0</零件13>
    <零件14>0</零件14>
    <零件15>0</零件15>
    <零件16>0</零件16>
    <零件17>0</零件17>
    <零件18>0</零件18>
    <零件19>0</零件19>
    <零件20>0</零件20>
    <零件21>0</零件21>
    <零件22>0</零件22>
    <零件23>0</零件23>
    <零件24>0</零件24>
    <零件25>0</零件25>
    <零件26>0</零件26>
    <零件27>0</零件27>
    <零件28>0</零件28>
    <零件29>0</零件29>
  </穴号>
  <组装偏心_X>
    <零件0>0</零件0>
    <零件1>0</零件1>
    <零件2>0</零件2>
    <零件3>0</零件3>
    <零件4>0</零件4>
    <零件5>0</零件5>
    <零件6>0</零件6>
    <零件7>0</零件7>
    <零件8>0</零件8>
    <零件9>0</零件9>
    <零件10>0</零件10>
    <零件11>0</零件11>
    <零件12>0</零件12>
    <零件13>0</零件13>
    <零件14>0</零件14>
    <零件15>0</零件15>
    <零件16>0</零件16>
    <零件17>0</零件17>
    <零件18>0</零件18>
    <零件19>0</零件19>
    <零件20>0</零件20>
    <零件21>0</零件21>
    <零件22>0</零件22>
    <零件23>0</零件23>
    <零件24>0</零件24>
    <零件25>0</零件25>
    <零件26>0</零件26>
    <零件27>0</零件27>
    <零件28>0</零件28>
    <零件29>0</零件29>
  </组装偏心_X>
  <组装偏心_Y>
    <零件0>0</零件0>
    <零件1>0</零件1>
    <零件2>0</零件2>
    <零件3>0</零件3>
    <零件4>0</零件4>
    <零件5>0</零件5>
    <零件6>0</零件6>
    <零件7>0</零件7>
    <零件8>0</零件8>
    <零件9>0</零件9>
    <零件10>0</零件10>
    <零件11>0</零件11>
    <零件12>0</零件12>
    <零件13>0</零件13>
    <零件14>0</零件14>
    <零件15>0</零件15>
    <零件16>0</零件16>
    <零件17>0</零件17>
    <零件18>0</零件18>
    <零件19>0</零件19>
    <零件20>0</零件20>
    <零件21>0</零件21>
    <零件22>0</零件22>
    <零件23>0</零件23>
    <零件24>0</零件24>
    <零件25>0</零件25>
    <零件26>0</零件26>
    <零件27>0</零件27>
    <零件28>0</零件28>
    <零件29>0</零件29>
  </组装偏心_Y>
  <偏心使能>
    <零件0>false</零件0>
    <零件1>false</零件1>
    <零件2>false</零件2>
    <零件3>false</零件3>
    <零件4>false</零件4>
    <零件5>false</零件5>
    <零件6>false</零件6>
    <零件7>false</零件7>
    <零件8>false</零件8>
    <零件9>false</零件9>
    <零件10>false</零件10>
    <零件11>false</零件11>
    <零件12>false</零件12>
    <零件13>false</零件13>
    <零件14>false</零件14>
    <零件15>false</零件15>
    <零件16>false</零件16>
    <零件17>false</零件17>
    <零件18>false</零件18>
    <零件19>false</零件19>
    <零件20>false</零件20>
    <零件21>false</零件21>
    <零件22>false</零件22>
    <零件23>false</零件23>
    <零件24>false</零件24>
    <零件25>false</零件25>
    <零件26>false</零件26>
    <零件27>false</零件27>
    <零件28>false</零件28>
    <零件29>false</零件29>
  </偏心使能>
  <压力分段数>
    <零件0>1</零件0>
    <零件1>1</零件1>
    <零件2>1</零件2>
    <零件3>1</零件3>
    <零件4>1</零件4>
    <零件5>1</零件5>
    <零件6>1</零件6>
    <零件7>1</零件7>
    <零件8>1</零件8>
    <零件9>1</零件9>
    <零件10>1</零件10>
    <零件11>1</零件11>
    <零件12>1</零件12>
    <零件13>1</零件13>
    <零件14>1</零件14>
    <零件15>1</零件15>
    <零件16>1</零件16>
    <零件17>1</零件17>
    <零件18>1</零件18>
    <零件19>1</零件19>
    <零件20>1</零件20>
    <零件21>1</零件21>
    <零件22>1</零件22>
    <零件23>1</零件23>
    <零件24>1</零件24>
    <零件25>1</零件25>
    <零件26>1</零件26>
    <零件27>1</零件27>
    <零件28>1</零件28>
    <零件29>1</零件29>
  </压力分段数>
  <组装吸气使能>
    <零件0>true</零件0>
    <零件1>true</零件1>
    <零件2>true</零件2>
    <零件3>true</零件3>
    <零件4>true</零件4>
    <零件5>true</零件5>
    <零件6>true</零件6>
    <零件7>true</零件7>
    <零件8>true</零件8>
    <零件9>true</零件9>
    <零件10>true</零件10>
    <零件11>true</零件11>
    <零件12>true</零件12>
    <零件13>true</零件13>
    <零件14>true</零件14>
    <零件15>true</零件15>
    <零件16>true</零件16>
    <零件17>true</零件17>
    <零件18>true</零件18>
    <零件19>true</零件19>
    <零件20>true</零件20>
    <零件21>true</零件21>
    <零件22>true</零件22>
    <零件23>true</零件23>
    <零件24>true</零件24>
    <零件25>true</零件25>
    <零件26>true</零件26>
    <零件27>true</零件27>
    <零件28>true</零件28>
    <零件29>true</零件29>
  </组装吸气使能>
  <拍照1_O>
    <零件0>0</零件0>
    <零件1>0</零件1>
    <零件2>0</零件2>
    <零件3>0</零件3>
    <零件4>0</零件4>
    <零件5>0</零件5>
    <零件6>0</零件6>
    <零件7>0</零件7>
    <零件8>0</零件8>
    <零件9>0</零件9>
    <零件10>0</零件10>
    <零件11>0</零件11>
    <零件12>0</零件12>
    <零件13>0</零件13>
    <零件14>0</零件14>
    <零件15>0</零件15>
    <零件16>0</零件16>
    <零件17>0</零件17>
    <零件18>0</零件18>
    <零件19>0</零件19>
    <零件20>0</零件20>
    <零件21>0</零件21>
    <零件22>0</零件22>
    <零件23>0</零件23>
    <零件24>0</零件24>
    <零件25>0</零件25>
    <零件26>0</零件26>
    <零件27>0</零件27>
    <零件28>0</零件28>
    <零件29>0</零件29>
  </拍照1_O>
  <拍照2_O>
    <零件0>1</零件0>
    <零件1>0</零件1>
    <零件2>0</零件2>
    <零件3>0</零件3>
    <零件4>0</零件4>
    <零件5>0</零件5>
    <零件6>0</零件6>
    <零件7>0</零件7>
    <零件8>0</零件8>
    <零件9>0</零件9>
    <零件10>0</零件10>
    <零件11>0</零件11>
    <零件12>0</零件12>
    <零件13>0</零件13>
    <零件14>0</零件14>
    <零件15>0</零件15>
    <零件16>0</零件16>
    <零件17>0</零件17>
    <零件18>0</零件18>
    <零件19>0</零件19>
    <零件20>0</零件20>
    <零件21>0</零件21>
    <零件22>0</零件22>
    <零件23>0</零件23>
    <零件24>0</零件24>
    <零件25>0</零件25>
    <零件26>0</零件26>
    <零件27>0</零件27>
    <零件28>0</零件28>
    <零件29>0</零件29>
  </拍照2_O>
  <拍照3_O>
    <零件0>0</零件0>
    <零件1>0</零件1>
    <零件2>0</零件2>
    <零件3>0</零件3>
    <零件4>0</零件4>
    <零件5>0</零件5>
    <零件6>0</零件6>
    <零件7>0</零件7>
    <零件8>0</零件8>
    <零件9>0</零件9>
    <零件10>0</零件10>
    <零件11>0</零件11>
    <零件12>0</零件12>
    <零件13>0</零件13>
    <零件14>0</零件14>
    <零件15>0</零件15>
    <零件16>0</零件16>
    <零件17>0</零件17>
    <零件18>0</零件18>
    <零件19>0</零件19>
    <零件20>0</零件20>
    <零件21>0</零件21>
    <零件22>0</零件22>
    <零件23>0</零件23>
    <零件24>0</零件24>
    <零件25>0</零件25>
    <零件26>0</零件26>
    <零件27>0</零件27>
    <零件28>0</零件28>
    <零件29>0</零件29>
  </拍照3_O>
  <拍照4_O>
    <零件0>0</零件0>
    <零件1>0</零件1>
    <零件2>0</零件2>
    <零件3>0</零件3>
    <零件4>0</零件4>
    <零件5>0</零件5>
    <零件6>0</零件6>
    <零件7>0</零件7>
    <零件8>0</零件8>
    <零件9>0</零件9>
    <零件10>0</零件10>
    <零件11>0</零件11>
    <零件12>0</零件12>
    <零件13>0</零件13>
    <零件14>0</零件14>
    <零件15>0</零件15>
    <零件16>0</零件16>
    <零件17>0</零件17>
    <零件18>0</零件18>
    <零件19>0</零件19>
    <零件20>0</零件20>
    <零件21>0</零件21>
    <零件22>0</零件22>
    <零件23>0</零件23>
    <零件24>0</零件24>
    <零件25>0</零件25>
    <零件26>0</零件26>
    <零件27>0</零件27>
    <零件28>0</零件28>
    <零件29>0</零件29>
  </拍照4_O>
  <拍照1_P>
    <零件0>0</零件0>
    <零件1>P1_1</零件1>
    <零件2>0</零件2>
    <零件3>P2_1</零件3>
    <零件4>0</零件4>
    <零件5>P3_1</零件5>
    <零件6>0</零件6>
    <零件7>P4_1</零件7>
    <零件8>S4_1</零件8>
    <零件9>0</零件9>
    <零件10>P5_1</零件10>
    <零件11>ST_1</零件11>
    <零件12>0</零件12>
    <零件13>0</零件13>
    <零件14>0</零件14>
    <零件15>0</零件15>
    <零件16>0</零件16>
    <零件17>0</零件17>
    <零件18>0</零件18>
    <零件19>0</零件19>
    <零件20>0</零件20>
    <零件21>0</零件21>
    <零件22>0</零件22>
    <零件23>0</零件23>
    <零件24>0</零件24>
    <零件25>0</零件25>
    <零件26>0</零件26>
    <零件27>0</零件27>
    <零件28>0</零件28>
    <零件29>0</零件29>
  </拍照1_P>
  <拍照2_P>
    <零件0>Barrel_2</零件0>
    <零件1>0</零件1>
    <零件2>0</零件2>
    <零件3>0</零件3>
    <零件4>0</零件4>
    <零件5>0</零件5>
    <零件6>0</零件6>
    <零件7>0</零件7>
    <零件8>0</零件8>
    <零件9>0</零件9>
    <零件10>0</零件10>
    <零件11>0</零件11>
    <零件12>0</零件12>
    <零件13>0</零件13>
    <零件14>0</零件14>
    <零件15>0</零件15>
    <零件16>0</零件16>
    <零件17>0</零件17>
    <零件18>0</零件18>
    <零件19>0</零件19>
    <零件20>0</零件20>
    <零件21>0</零件21>
    <零件22>0</零件22>
    <零件23>0</零件23>
    <零件24>0</零件24>
    <零件25>0</零件25>
    <零件26>0</零件26>
    <零件27>0</零件27>
    <零件28>0</零件28>
    <零件29>0</零件29>
  </拍照2_P>
  <拍照3_P>
    <零件0>0</零件0>
    <零件1>P1_3</零件1>
    <零件2>S1_3</零件2>
    <零件3>P2_3</零件3>
    <零件4>S2_3</零件4>
    <零件5>P3_3</零件5>
    <零件6>S3_3</零件6>
    <零件7>P4_3</零件7>
    <零件8>S4_3</零件8>
    <零件9>S5_3</零件9>
    <零件10>P5_3</零件10>
    <零件11>ST_3</零件11>
    <零件12>0</零件12>
    <零件13>0</零件13>
    <零件14>0</零件14>
    <零件15>0</零件15>
    <零件16>0</零件16>
    <零件17>0</零件17>
    <零件18>0</零件18>
    <零件19>0</零件19>
    <零件20>0</零件20>
    <零件21>0</零件21>
    <零件22>0</零件22>
    <零件23>0</零件23>
    <零件24>0</零件24>
    <零件25>0</零件25>
    <零件26>0</零件26>
    <零件27>0</零件27>
    <零件28>0</零件28>
    <零件29>0</零件29>
  </拍照3_P>
  <拍照4_P>
    <零件0>0</零件0>
    <零件1>P1_4</零件1>
    <零件2>S1_4</零件2>
    <零件3>P2_4</零件3>
    <零件4>S2_4</零件4>
    <零件5>P3_4</零件5>
    <零件6>S3_4</零件6>
    <零件7>P4_4</零件7>
    <零件8>S4_4</零件8>
    <零件9>S5_4</零件9>
    <零件10>P5_4</零件10>
    <零件11>ST_4</零件11>
    <零件12>0</零件12>
    <零件13>0</零件13>
    <零件14>0</零件14>
    <零件15>0</零件15>
    <零件16>0</零件16>
    <零件17>0</零件17>
    <零件18>0</零件18>
    <零件19>0</零件19>
    <零件20>0</零件20>
    <零件21>0</零件21>
    <零件22>0</零件22>
    <零件23>0</零件23>
    <零件24>0</零件24>
    <零件25>0</零件25>
    <零件26>0</零件26>
    <零件27>0</零件27>
    <零件28>0</零件28>
    <零件29>0</零件29>
  </拍照4_P>
  <拍照1_X>
    <零件0>0</零件0>
    <零件1>0</零件1>
    <零件2>0</零件2>
    <零件3>0</零件3>
    <零件4>0</零件4>
    <零件5>0</零件5>
    <零件6>0</零件6>
    <零件7>0</零件7>
    <零件8>0</零件8>
    <零件9>0</零件9>
    <零件10>0</零件10>
    <零件11>0</零件11>
    <零件12>0</零件12>
    <零件13>0</零件13>
    <零件14>0</零件14>
    <零件15>0</零件15>
    <零件16>0</零件16>
    <零件17>0</零件17>
    <零件18>0</零件18>
    <零件19>0</零件19>
    <零件20>0</零件20>
    <零件21>0</零件21>
    <零件22>0</零件22>
    <零件23>0</零件23>
    <零件24>0</零件24>
    <零件25>0</零件25>
    <零件26>0</零件26>
    <零件27>0</零件27>
    <零件28>0</零件28>
    <零件29>0</零件29>
  </拍照1_X>
  <拍照2_X>
    <零件0>0</零件0>
    <零件1>0</零件1>
    <零件2>0</零件2>
    <零件3>0</零件3>
    <零件4>0</零件4>
    <零件5>0</零件5>
    <零件6>0</零件6>
    <零件7>0</零件7>
    <零件8>0</零件8>
    <零件9>0</零件9>
    <零件10>0</零件10>
    <零件11>0</零件11>
    <零件12>0</零件12>
    <零件13>0</零件13>
    <零件14>0</零件14>
    <零件15>0</零件15>
    <零件16>0</零件16>
    <零件17>0</零件17>
    <零件18>0</零件18>
    <零件19>0</零件19>
    <零件20>0</零件20>
    <零件21>0</零件21>
    <零件22>0</零件22>
    <零件23>0</零件23>
    <零件24>0</零件24>
    <零件25>0</零件25>
    <零件26>0</零件26>
    <零件27>0</零件27>
    <零件28>0</零件28>
    <零件29>0</零件29>
  </拍照2_X>
  <拍照3_X>
    <零件0>0</零件0>
    <零件1>0</零件1>
    <零件2>0</零件2>
    <零件3>0</零件3>
    <零件4>0</零件4>
    <零件5>0</零件5>
    <零件6>0</零件6>
    <零件7>0</零件7>
    <零件8>0</零件8>
    <零件9>0</零件9>
    <零件10>0</零件10>
    <零件11>0</零件11>
    <零件12>0</零件12>
    <零件13>0</零件13>
    <零件14>0</零件14>
    <零件15>0</零件15>
    <零件16>0</零件16>
    <零件17>0</零件17>
    <零件18>0</零件18>
    <零件19>0</零件19>
    <零件20>0</零件20>
    <零件21>0</零件21>
    <零件22>0</零件22>
    <零件23>0</零件23>
    <零件24>0</零件24>
    <零件25>0</零件25>
    <零件26>0</零件26>
    <零件27>0</零件27>
    <零件28>0</零件28>
    <零件29>0</零件29>
  </拍照3_X>
  <拍照4_X>
    <零件0>0</零件0>
    <零件1>0</零件1>
    <零件2>0</零件2>
    <零件3>0</零件3>
    <零件4>0</零件4>
    <零件5>0</零件5>
    <零件6>0</零件6>
    <零件7>0</零件7>
    <零件8>0</零件8>
    <零件9>0</零件9>
    <零件10>0</零件10>
    <零件11>0</零件11>
    <零件12>0</零件12>
    <零件13>0</零件13>
    <零件14>0</零件14>
    <零件15>0</零件15>
    <零件16>0</零件16>
    <零件17>0</零件17>
    <零件18>0</零件18>
    <零件19>0</零件19>
    <零件20>0</零件20>
    <零件21>0</零件21>
    <零件22>0</零件22>
    <零件23>0</零件23>
    <零件24>0</零件24>
    <零件25>0</零件25>
    <零件26>0</零件26>
    <零件27>0</零件27>
    <零件28>0</零件28>
    <零件29>0</零件29>
  </拍照4_X>
  <拍照1_Y>
    <零件0>0</零件0>
    <零件1>0</零件1>
    <零件2>0</零件2>
    <零件3>0</零件3>
    <零件4>0</零件4>
    <零件5>0</零件5>
    <零件6>0</零件6>
    <零件7>0</零件7>
    <零件8>0</零件8>
    <零件9>0</零件9>
    <零件10>0</零件10>
    <零件11>0</零件11>
    <零件12>0</零件12>
    <零件13>0</零件13>
    <零件14>0</零件14>
    <零件15>0</零件15>
    <零件16>0</零件16>
    <零件17>0</零件17>
    <零件18>0</零件18>
    <零件19>0</零件19>
    <零件20>0</零件20>
    <零件21>0</零件21>
    <零件22>0</零件22>
    <零件23>0</零件23>
    <零件24>0</零件24>
    <零件25>0</零件25>
    <零件26>0</零件26>
    <零件27>0</零件27>
    <零件28>0</零件28>
    <零件29>0</零件29>
  </拍照1_Y>
  <拍照2_Y>
    <零件0>0</零件0>
    <零件1>0</零件1>
    <零件2>0</零件2>
    <零件3>0</零件3>
    <零件4>0</零件4>
    <零件5>0</零件5>
    <零件6>0</零件6>
    <零件7>0</零件7>
    <零件8>0</零件8>
    <零件9>0</零件9>
    <零件10>0</零件10>
    <零件11>0</零件11>
    <零件12>0</零件12>
    <零件13>0</零件13>
    <零件14>0</零件14>
    <零件15>0</零件15>
    <零件16>0</零件16>
    <零件17>0</零件17>
    <零件18>0</零件18>
    <零件19>0</零件19>
    <零件20>0</零件20>
    <零件21>0</零件21>
    <零件22>0</零件22>
    <零件23>0</零件23>
    <零件24>0</零件24>
    <零件25>0</零件25>
    <零件26>0</零件26>
    <零件27>0</零件27>
    <零件28>0</零件28>
    <零件29>0</零件29>
  </拍照2_Y>
  <拍照3_Y>
    <零件0>0</零件0>
    <零件1>0</零件1>
    <零件2>0</零件2>
    <零件3>0</零件3>
    <零件4>0</零件4>
    <零件5>0</零件5>
    <零件6>0</零件6>
    <零件7>0</零件7>
    <零件8>0</零件8>
    <零件9>0</零件9>
    <零件10>0</零件10>
    <零件11>0</零件11>
    <零件12>0</零件12>
    <零件13>0</零件13>
    <零件14>0</零件14>
    <零件15>0</零件15>
    <零件16>0</零件16>
    <零件17>0</零件17>
    <零件18>0</零件18>
    <零件19>0</零件19>
    <零件20>0</零件20>
    <零件21>0</零件21>
    <零件22>0</零件22>
    <零件23>0</零件23>
    <零件24>0</零件24>
    <零件25>0</零件25>
    <零件26>0</零件26>
    <零件27>0</零件27>
    <零件28>0</零件28>
    <零件29>0</零件29>
  </拍照3_Y>
  <拍照4_Y>
    <零件0>0</零件0>
    <零件1>0</零件1>
    <零件2>0</零件2>
    <零件3>0</零件3>
    <零件4>0</零件4>
    <零件5>0</零件5>
    <零件6>0</零件6>
    <零件7>0</零件7>
    <零件8>0</零件8>
    <零件9>0</零件9>
    <零件10>0</零件10>
    <零件11>0</零件11>
    <零件12>0</零件12>
    <零件13>0</零件13>
    <零件14>0</零件14>
    <零件15>0</零件15>
    <零件16>0</零件16>
    <零件17>0</零件17>
    <零件18>0</零件18>
    <零件19>0</零件19>
    <零件20>0</零件20>
    <零件21>0</零件21>
    <零件22>0</零件22>
    <零件23>0</零件23>
    <零件24>0</零件24>
    <零件25>0</零件25>
    <零件26>0</零件26>
    <零件27>0</零件27>
    <零件28>0</零件28>
    <零件29>0</零件29>
  </拍照4_Y>
  <拍照1_CX>
    <零件0>00</零件0>
    <零件1>00</零件1>
    <零件2>00</零件2>
    <零件3>00</零件3>
    <零件4>00</零件4>
    <零件5>00</零件5>
    <零件6>00</零件6>
    <零件7>00</零件7>
    <零件8>00</零件8>
    <零件9>00</零件9>
    <零件10>00</零件10>
    <零件11>00</零件11>
    <零件12>00</零件12>
    <零件13>00</零件13>
    <零件14>00</零件14>
    <零件15>00</零件15>
    <零件16>00</零件16>
    <零件17>00</零件17>
    <零件18>00</零件18>
    <零件19>00</零件19>
    <零件20>00</零件20>
    <零件21>00</零件21>
    <零件22>00</零件22>
    <零件23>00</零件23>
    <零件24>00</零件24>
    <零件25>00</零件25>
    <零件26>00</零件26>
    <零件27>00</零件27>
    <零件28>00</零件28>
    <零件29>00</零件29>
  </拍照1_CX>
  <拍照4_CX>
    <零件0>00</零件0>
    <零件1>00</零件1>
    <零件2>00</零件2>
    <零件3>00</零件3>
    <零件4>00</零件4>
    <零件5>00</零件5>
    <零件6>00</零件6>
    <零件7>00</零件7>
    <零件8>00</零件8>
    <零件9>00</零件9>
    <零件10>00</零件10>
    <零件11>00</零件11>
    <零件12>00</零件12>
    <零件13>00</零件13>
    <零件14>00</零件14>
    <零件15>00</零件15>
    <零件16>00</零件16>
    <零件17>00</零件17>
    <零件18>00</零件18>
    <零件19>00</零件19>
    <零件20>00</零件20>
    <零件21>00</零件21>
    <零件22>00</零件22>
    <零件23>00</零件23>
    <零件24>00</零件24>
    <零件25>00</零件25>
    <零件26>00</零件26>
    <零件27>00</零件27>
    <零件28>00</零件28>
    <零件29>00</零件29>
  </拍照4_CX>
  <换夹具_CX>
    <零件0>00</零件0>
    <零件1>00</零件1>
    <零件2>00</零件2>
    <零件3>00</零件3>
    <零件4>00</零件4>
    <零件5>00</零件5>
    <零件6>00</零件6>
    <零件7>00</零件7>
    <零件8>00</零件8>
    <零件9>00</零件9>
    <零件10>00</零件10>
    <零件11>00</零件11>
    <零件12>00</零件12>
    <零件13>00</零件13>
    <零件14>00</零件14>
    <零件15>00</零件15>
    <零件16>00</零件16>
    <零件17>00</零件17>
    <零件18>00</零件18>
    <零件19>00</零件19>
    <零件20>00</零件20>
    <零件21>00</零件21>
    <零件22>00</零件22>
    <零件23>00</零件23>
    <零件24>00</零件24>
    <零件25>00</零件25>
    <零件26>00</零件26>
    <零件27>00</零件27>
    <零件28>00</零件28>
    <零件29>00</零件29>
  </换夹具_CX>
  <吸零件_CX>
    <零件0>00</零件0>
    <零件1>00</零件1>
    <零件2>00</零件2>
    <零件3>00</零件3>
    <零件4>00</零件4>
    <零件5>00</零件5>
    <零件6>00</零件6>
    <零件7>00</零件7>
    <零件8>00</零件8>
    <零件9>00</零件9>
    <零件10>00</零件10>
    <零件11>00</零件11>
    <零件12>00</零件12>
    <零件13>00</零件13>
    <零件14>00</零件14>
    <零件15>00</零件15>
    <零件16>00</零件16>
    <零件17>00</零件17>
    <零件18>00</零件18>
    <零件19>00</零件19>
    <零件20>00</零件20>
    <零件21>00</零件21>
    <零件22>00</零件22>
    <零件23>00</零件23>
    <零件24>00</零件24>
    <零件25>00</零件25>
    <零件26>00</零件26>
    <零件27>00</零件27>
    <零件28>00</零件28>
    <零件29>00</零件29>
  </吸零件_CX>
  <拍照2_CX>
    <零件0>00</零件0>
    <零件1>00</零件1>
    <零件2>00</零件2>
    <零件3>00</零件3>
    <零件4>00</零件4>
    <零件5>00</零件5>
    <零件6>00</零件6>
    <零件7>00</零件7>
    <零件8>00</零件8>
    <零件9>00</零件9>
    <零件10>00</零件10>
    <零件11>00</零件11>
    <零件12>00</零件12>
    <零件13>00</零件13>
    <零件14>00</零件14>
    <零件15>00</零件15>
    <零件16>00</零件16>
    <零件17>00</零件17>
    <零件18>00</零件18>
    <零件19>00</零件19>
    <零件20>00</零件20>
    <零件21>00</零件21>
    <零件22>00</零件22>
    <零件23>00</零件23>
    <零件24>00</零件24>
    <零件25>00</零件25>
    <零件26>00</零件26>
    <零件27>00</零件27>
    <零件28>00</零件28>
    <零件29>00</零件29>
  </拍照2_CX>
  <拍照3_CX>
    <零件0>00</零件0>
    <零件1>00</零件1>
    <零件2>00</零件2>
    <零件3>00</零件3>
    <零件4>00</零件4>
    <零件5>00</零件5>
    <零件6>00</零件6>
    <零件7>00</零件7>
    <零件8>00</零件8>
    <零件9>00</零件9>
    <零件10>00</零件10>
    <零件11>00</零件11>
    <零件12>00</零件12>
    <零件13>00</零件13>
    <零件14>00</零件14>
    <零件15>00</零件15>
    <零件16>00</零件16>
    <零件17>00</零件17>
    <零件18>00</零件18>
    <零件19>00</零件19>
    <零件20>00</零件20>
    <零件21>00</零件21>
    <零件22>00</零件22>
    <零件23>00</零件23>
    <零件24>00</零件24>
    <零件25>00</零件25>
    <零件26>00</零件26>
    <零件27>00</零件27>
    <零件28>00</零件28>
    <零件29>00</零件29>
  </拍照3_CX>
  <组装_CX>
    <零件0>00</零件0>
    <零件1>34</零件1>
    <零件2>34</零件2>
    <零件3>34</零件3>
    <零件4>34</零件4>
    <零件5>34</零件5>
    <零件6>34</零件6>
    <零件7>34</零件7>
    <零件8>34</零件8>
    <零件9>34</零件9>
    <零件10>34</零件10>
    <零件11>34</零件11>
    <零件12>00</零件12>
    <零件13>00</零件13>
    <零件14>00</零件14>
    <零件15>00</零件15>
    <零件16>00</零件16>
    <零件17>00</零件17>
    <零件18>00</零件18>
    <零件19>00</零件19>
    <零件20>00</零件20>
    <零件21>00</零件21>
    <零件22>00</零件22>
    <零件23>00</零件23>
    <零件24>00</零件24>
    <零件25>00</零件25>
    <零件26>00</零件26>
    <零件27>00</零件27>
    <零件28>00</零件28>
    <零件29>00</零件29>
  </组装_CX>
  <放夹具_CX>
    <零件0>00</零件0>
    <零件1>00</零件1>
    <零件2>00</零件2>
    <零件3>00</零件3>
    <零件4>00</零件4>
    <零件5>00</零件5>
    <零件6>00</零件6>
    <零件7>00</零件7>
    <零件8>00</零件8>
    <零件9>00</零件9>
    <零件10>00</零件10>
    <零件11>00</零件11>
    <零件12>00</零件12>
    <零件13>00</零件13>
    <零件14>00</零件14>
    <零件15>00</零件15>
    <零件16>00</零件16>
    <零件17>00</零件17>
    <零件18>00</零件18>
    <零件19>00</零件19>
    <零件20>00</零件20>
    <零件21>00</零件21>
    <零件22>00</零件22>
    <零件23>00</零件23>
    <零件24>00</零件24>
    <零件25>00</零件25>
    <零件26>00</零件26>
    <零件27>00</零件27>
    <零件28>00</零件28>
    <零件29>00</零件29>
  </放夹具_CX>
  <拍照1_CY>
    <零件0>00</零件0>
    <零件1>00</零件1>
    <零件2>00</零件2>
    <零件3>00</零件3>
    <零件4>00</零件4>
    <零件5>00</零件5>
    <零件6>00</零件6>
    <零件7>00</零件7>
    <零件8>00</零件8>
    <零件9>00</零件9>
    <零件10>00</零件10>
    <零件11>00</零件11>
    <零件12>00</零件12>
    <零件13>00</零件13>
    <零件14>00</零件14>
    <零件15>00</零件15>
    <零件16>00</零件16>
    <零件17>00</零件17>
    <零件18>00</零件18>
    <零件19>00</零件19>
    <零件20>00</零件20>
    <零件21>00</零件21>
    <零件22>00</零件22>
    <零件23>00</零件23>
    <零件24>00</零件24>
    <零件25>00</零件25>
    <零件26>00</零件26>
    <零件27>00</零件27>
    <零件28>00</零件28>
    <零件29>00</零件29>
  </拍照1_CY>
  <拍照4_CY>
    <零件0>00</零件0>
    <零件1>00</零件1>
    <零件2>00</零件2>
    <零件3>00</零件3>
    <零件4>00</零件4>
    <零件5>00</零件5>
    <零件6>00</零件6>
    <零件7>00</零件7>
    <零件8>00</零件8>
    <零件9>00</零件9>
    <零件10>00</零件10>
    <零件11>00</零件11>
    <零件12>00</零件12>
    <零件13>00</零件13>
    <零件14>00</零件14>
    <零件15>00</零件15>
    <零件16>00</零件16>
    <零件17>00</零件17>
    <零件18>00</零件18>
    <零件19>00</零件19>
    <零件20>00</零件20>
    <零件21>00</零件21>
    <零件22>00</零件22>
    <零件23>00</零件23>
    <零件24>00</零件24>
    <零件25>00</零件25>
    <零件26>00</零件26>
    <零件27>00</零件27>
    <零件28>00</零件28>
    <零件29>00</零件29>
  </拍照4_CY>
  <换夹具_CY>
    <零件0>00</零件0>
    <零件1>00</零件1>
    <零件2>00</零件2>
    <零件3>00</零件3>
    <零件4>00</零件4>
    <零件5>00</零件5>
    <零件6>00</零件6>
    <零件7>00</零件7>
    <零件8>00</零件8>
    <零件9>00</零件9>
    <零件10>00</零件10>
    <零件11>00</零件11>
    <零件12>00</零件12>
    <零件13>00</零件13>
    <零件14>00</零件14>
    <零件15>00</零件15>
    <零件16>00</零件16>
    <零件17>00</零件17>
    <零件18>00</零件18>
    <零件19>00</零件19>
    <零件20>00</零件20>
    <零件21>00</零件21>
    <零件22>00</零件22>
    <零件23>00</零件23>
    <零件24>00</零件24>
    <零件25>00</零件25>
    <零件26>00</零件26>
    <零件27>00</零件27>
    <零件28>00</零件28>
    <零件29>00</零件29>
  </换夹具_CY>
  <吸零件_CY>
    <零件0>00</零件0>
    <零件1>00</零件1>
    <零件2>00</零件2>
    <零件3>00</零件3>
    <零件4>00</零件4>
    <零件5>00</零件5>
    <零件6>00</零件6>
    <零件7>00</零件7>
    <零件8>00</零件8>
    <零件9>00</零件9>
    <零件10>00</零件10>
    <零件11>00</零件11>
    <零件12>00</零件12>
    <零件13>00</零件13>
    <零件14>00</零件14>
    <零件15>00</零件15>
    <零件16>00</零件16>
    <零件17>00</零件17>
    <零件18>00</零件18>
    <零件19>00</零件19>
    <零件20>00</零件20>
    <零件21>00</零件21>
    <零件22>00</零件22>
    <零件23>00</零件23>
    <零件24>00</零件24>
    <零件25>00</零件25>
    <零件26>00</零件26>
    <零件27>00</零件27>
    <零件28>00</零件28>
    <零件29>00</零件29>
  </吸零件_CY>
  <拍照2_CY>
    <零件0>00</零件0>
    <零件1>00</零件1>
    <零件2>00</零件2>
    <零件3>00</零件3>
    <零件4>00</零件4>
    <零件5>00</零件5>
    <零件6>00</零件6>
    <零件7>00</零件7>
    <零件8>00</零件8>
    <零件9>00</零件9>
    <零件10>00</零件10>
    <零件11>00</零件11>
    <零件12>00</零件12>
    <零件13>00</零件13>
    <零件14>00</零件14>
    <零件15>00</零件15>
    <零件16>00</零件16>
    <零件17>00</零件17>
    <零件18>00</零件18>
    <零件19>00</零件19>
    <零件20>00</零件20>
    <零件21>00</零件21>
    <零件22>00</零件22>
    <零件23>00</零件23>
    <零件24>00</零件24>
    <零件25>00</零件25>
    <零件26>00</零件26>
    <零件27>00</零件27>
    <零件28>00</零件28>
    <零件29>00</零件29>
  </拍照2_CY>
  <拍照3_CY>
    <零件0>00</零件0>
    <零件1>00</零件1>
    <零件2>00</零件2>
    <零件3>00</零件3>
    <零件4>00</零件4>
    <零件5>00</零件5>
    <零件6>00</零件6>
    <零件7>00</零件7>
    <零件8>00</零件8>
    <零件9>00</零件9>
    <零件10>00</零件10>
    <零件11>00</零件11>
    <零件12>00</零件12>
    <零件13>00</零件13>
    <零件14>00</零件14>
    <零件15>00</零件15>
    <零件16>00</零件16>
    <零件17>00</零件17>
    <零件18>00</零件18>
    <零件19>00</零件19>
    <零件20>00</零件20>
    <零件21>00</零件21>
    <零件22>00</零件22>
    <零件23>00</零件23>
    <零件24>00</零件24>
    <零件25>00</零件25>
    <零件26>00</零件26>
    <零件27>00</零件27>
    <零件28>00</零件28>
    <零件29>00</零件29>
  </拍照3_CY>
  <组装_CY>
    <零件0>00</零件0>
    <零件1>34</零件1>
    <零件2>34</零件2>
    <零件3>34</零件3>
    <零件4>34</零件4>
    <零件5>34</零件5>
    <零件6>34</零件6>
    <零件7>34</零件7>
    <零件8>34</零件8>
    <零件9>34</零件9>
    <零件10>34</零件10>
    <零件11>34</零件11>
    <零件12>00</零件12>
    <零件13>00</零件13>
    <零件14>00</零件14>
    <零件15>00</零件15>
    <零件16>00</零件16>
    <零件17>00</零件17>
    <零件18>00</零件18>
    <零件19>00</零件19>
    <零件20>00</零件20>
    <零件21>00</零件21>
    <零件22>00</零件22>
    <零件23>00</零件23>
    <零件24>00</零件24>
    <零件25>00</零件25>
    <零件26>00</零件26>
    <零件27>00</零件27>
    <零件28>00</零件28>
    <零件29>00</零件29>
  </组装_CY>
  <放夹具_CY>
    <零件0>00</零件0>
    <零件1>00</零件1>
    <零件2>00</零件2>
    <零件3>00</零件3>
    <零件4>00</零件4>
    <零件5>00</零件5>
    <零件6>00</零件6>
    <零件7>00</零件7>
    <零件8>00</零件8>
    <零件9>00</零件9>
    <零件10>00</零件10>
    <零件11>00</零件11>
    <零件12>00</零件12>
    <零件13>00</零件13>
    <零件14>00</零件14>
    <零件15>00</零件15>
    <零件16>00</零件16>
    <零件17>00</零件17>
    <零件18>00</零件18>
    <零件19>00</零件19>
    <零件20>00</零件20>
    <零件21>00</零件21>
    <零件22>00</零件22>
    <零件23>00</零件23>
    <零件24>00</零件24>
    <零件25>00</零件25>
    <零件26>00</零件26>
    <零件27>00</零件27>
    <零件28>00</零件28>
    <零件29>00</零件29>
  </放夹具_CY>
  <拍照1_CA>
    <零件0>00</零件0>
    <零件1>00</零件1>
    <零件2>00</零件2>
    <零件3>00</零件3>
    <零件4>00</零件4>
    <零件5>00</零件5>
    <零件6>00</零件6>
    <零件7>00</零件7>
    <零件8>00</零件8>
    <零件9>00</零件9>
    <零件10>00</零件10>
    <零件11>00</零件11>
    <零件12>00</零件12>
    <零件13>00</零件13>
    <零件14>00</零件14>
    <零件15>00</零件15>
    <零件16>00</零件16>
    <零件17>00</零件17>
    <零件18>00</零件18>
    <零件19>00</零件19>
    <零件20>00</零件20>
    <零件21>00</零件21>
    <零件22>00</零件22>
    <零件23>00</零件23>
    <零件24>00</零件24>
    <零件25>00</零件25>
    <零件26>00</零件26>
    <零件27>00</零件27>
    <零件28>00</零件28>
    <零件29>00</零件29>
  </拍照1_CA>
  <拍照4_CA>
    <零件0>0</零件0>
    <零件1>1</零件1>
    <零件2>0</零件2>
    <零件3>1</零件3>
    <零件4>0</零件4>
    <零件5>1</零件5>
    <零件6>0</零件6>
    <零件7>1</零件7>
    <零件8>1</零件8>
    <零件9>0</零件9>
    <零件10>1</零件10>
    <零件11>1</零件11>
    <零件12>0</零件12>
    <零件13>0</零件13>
    <零件14>0</零件14>
    <零件15>0</零件15>
    <零件16>0</零件16>
    <零件17>0</零件17>
    <零件18>0</零件18>
    <零件19>0</零件19>
    <零件20>0</零件20>
    <零件21>0</零件21>
    <零件22>0</零件22>
    <零件23>0</零件23>
    <零件24>0</零件24>
    <零件25>0</零件25>
    <零件26>0</零件26>
    <零件27>0</零件27>
    <零件28>0</零件28>
    <零件29>0</零件29>
  </拍照4_CA>
  <换夹具_CA>
    <零件0>0</零件0>
    <零件1>1</零件1>
    <零件2>0</零件2>
    <零件3>1</零件3>
    <零件4>0</零件4>
    <零件5>1</零件5>
    <零件6>0</零件6>
    <零件7>1</零件7>
    <零件8>1</零件8>
    <零件9>0</零件9>
    <零件10>1</零件10>
    <零件11>1</零件11>
    <零件12>0</零件12>
    <零件13>0</零件13>
    <零件14>0</零件14>
    <零件15>0</零件15>
    <零件16>0</零件16>
    <零件17>0</零件17>
    <零件18>0</零件18>
    <零件19>0</零件19>
    <零件20>0</零件20>
    <零件21>0</零件21>
    <零件22>0</零件22>
    <零件23>0</零件23>
    <零件24>0</零件24>
    <零件25>0</零件25>
    <零件26>0</零件26>
    <零件27>0</零件27>
    <零件28>0</零件28>
    <零件29>0</零件29>
  </换夹具_CA>
  <吸零件_CA>
    <零件0>0</零件0>
    <零件1>1</零件1>
    <零件2>0</零件2>
    <零件3>1</零件3>
    <零件4>0</零件4>
    <零件5>1</零件5>
    <零件6>0</零件6>
    <零件7>1</零件7>
    <零件8>1</零件8>
    <零件9>0</零件9>
    <零件10>1</零件10>
    <零件11>1</零件11>
    <零件12>0</零件12>
    <零件13>0</零件13>
    <零件14>0</零件14>
    <零件15>0</零件15>
    <零件16>0</零件16>
    <零件17>0</零件17>
    <零件18>0</零件18>
    <零件19>0</零件19>
    <零件20>0</零件20>
    <零件21>0</零件21>
    <零件22>0</零件22>
    <零件23>0</零件23>
    <零件24>0</零件24>
    <零件25>0</零件25>
    <零件26>0</零件26>
    <零件27>0</零件27>
    <零件28>0</零件28>
    <零件29>0</零件29>
  </吸零件_CA>
  <拍照2_CA>
    <零件0>0</零件0>
    <零件1>1</零件1>
    <零件2>0</零件2>
    <零件3>1</零件3>
    <零件4>0</零件4>
    <零件5>1</零件5>
    <零件6>0</零件6>
    <零件7>1</零件7>
    <零件8>1</零件8>
    <零件9>0</零件9>
    <零件10>1</零件10>
    <零件11>1</零件11>
    <零件12>0</零件12>
    <零件13>0</零件13>
    <零件14>0</零件14>
    <零件15>0</零件15>
    <零件16>0</零件16>
    <零件17>0</零件17>
    <零件18>0</零件18>
    <零件19>0</零件19>
    <零件20>0</零件20>
    <零件21>0</零件21>
    <零件22>0</零件22>
    <零件23>0</零件23>
    <零件24>0</零件24>
    <零件25>0</零件25>
    <零件26>0</零件26>
    <零件27>0</零件27>
    <零件28>0</零件28>
    <零件29>0</零件29>
  </拍照2_CA>
  <拍照3_CA>
    <零件0>0</零件0>
    <零件1>1</零件1>
    <零件2>0</零件2>
    <零件3>1</零件3>
    <零件4>0</零件4>
    <零件5>1</零件5>
    <零件6>0</零件6>
    <零件7>1</零件7>
    <零件8>1</零件8>
    <零件9>0</零件9>
    <零件10>1</零件10>
    <零件11>1</零件11>
    <零件12>0</零件12>
    <零件13>0</零件13>
    <零件14>0</零件14>
    <零件15>0</零件15>
    <零件16>0</零件16>
    <零件17>0</零件17>
    <零件18>0</零件18>
    <零件19>0</零件19>
    <零件20>0</零件20>
    <零件21>0</零件21>
    <零件22>0</零件22>
    <零件23>0</零件23>
    <零件24>0</零件24>
    <零件25>0</零件25>
    <零件26>0</零件26>
    <零件27>0</零件27>
    <零件28>0</零件28>
    <零件29>0</零件29>
  </拍照3_CA>
  <组装_CA>
    <零件0>2</零件0>
    <零件1>1</零件1>
    <零件2>0</零件2>
    <零件3>1</零件3>
    <零件4>0</零件4>
    <零件5>1</零件5>
    <零件6>0</零件6>
    <零件7>1</零件7>
    <零件8>1</零件8>
    <零件9>0</零件9>
    <零件10>1</零件10>
    <零件11>1</零件11>
    <零件12>0</零件12>
    <零件13>0</零件13>
    <零件14>0</零件14>
    <零件15>0</零件15>
    <零件16>0</零件16>
    <零件17>0</零件17>
    <零件18>0</零件18>
    <零件19>0</零件19>
    <零件20>0</零件20>
    <零件21>0</零件21>
    <零件22>0</零件22>
    <零件23>0</零件23>
    <零件24>0</零件24>
    <零件25>0</零件25>
    <零件26>0</零件26>
    <零件27>0</零件27>
    <零件28>0</零件28>
    <零件29>0</零件29>
  </组装_CA>
  <放夹具_CA>
    <零件0>0</零件0>
    <零件1>0</零件1>
    <零件2>0</零件2>
    <零件3>0</零件3>
    <零件4>0</零件4>
    <零件5>0</零件5>
    <零件6>0</零件6>
    <零件7>0</零件7>
    <零件8>0</零件8>
    <零件9>0</零件9>
    <零件10>0</零件10>
    <零件11>0</零件11>
    <零件12>0</零件12>
    <零件13>0</零件13>
    <零件14>0</零件14>
    <零件15>0</零件15>
    <零件16>0</零件16>
    <零件17>0</零件17>
    <零件18>0</零件18>
    <零件19>0</零件19>
    <零件20>0</零件20>
    <零件21>0</零件21>
    <零件22>0</零件22>
    <零件23>0</零件23>
    <零件24>0</零件24>
    <零件25>0</零件25>
    <零件26>0</零件26>
    <零件27>0</零件27>
    <零件28>0</零件28>
    <零件29>0</零件29>
  </放夹具_CA>
  <分段压力1>
    <零件0>0</零件0>
    <零件1>0</零件1>
    <零件2>0</零件2>
    <零件3>0</零件3>
    <零件4>0</零件4>
    <零件5>0</零件5>
    <零件6>0</零件6>
    <零件7>0</零件7>
    <零件8>0</零件8>
    <零件9>0</零件9>
    <零件10>0</零件10>
    <零件11>0</零件11>
    <零件12>0</零件12>
    <零件13>0</零件13>
    <零件14>0</零件14>
    <零件15>0</零件15>
    <零件16>0</零件16>
    <零件17>0</零件17>
    <零件18>0</零件18>
    <零件19>0</零件19>
    <零件20>0</零件20>
    <零件21>0</零件21>
    <零件22>0</零件22>
    <零件23>0</零件23>
    <零件24>0</零件24>
    <零件25>0</零件25>
    <零件26>0</零件26>
    <零件27>0</零件27>
    <零件28>0</零件28>
    <零件29>0</零件29>
  </分段压力1>
  <分段压力2>
    <零件0>0</零件0>
    <零件1>0</零件1>
    <零件2>0</零件2>
    <零件3>0</零件3>
    <零件4>0</零件4>
    <零件5>0</零件5>
    <零件6>0</零件6>
    <零件7>0</零件7>
    <零件8>0</零件8>
    <零件9>0</零件9>
    <零件10>0</零件10>
    <零件11>0</零件11>
    <零件12>0</零件12>
    <零件13>0</零件13>
    <零件14>0</零件14>
    <零件15>0</零件15>
    <零件16>0</零件16>
    <零件17>0</零件17>
    <零件18>0</零件18>
    <零件19>0</零件19>
    <零件20>0</零件20>
    <零件21>0</零件21>
    <零件22>0</零件22>
    <零件23>0</零件23>
    <零件24>0</零件24>
    <零件25>0</零件25>
    <零件26>0</零件26>
    <零件27>0</零件27>
    <零件28>0</零件28>
    <零件29>0</零件29>
  </分段压力2>
  <分段压力3>
    <零件0>0</零件0>
    <零件1>0</零件1>
    <零件2>0</零件2>
    <零件3>0</零件3>
    <零件4>0</零件4>
    <零件5>0</零件5>
    <零件6>0</零件6>
    <零件7>0</零件7>
    <零件8>0</零件8>
    <零件9>0</零件9>
    <零件10>0</零件10>
    <零件11>0</零件11>
    <零件12>0</零件12>
    <零件13>0</零件13>
    <零件14>0</零件14>
    <零件15>0</零件15>
    <零件16>0</零件16>
    <零件17>0</零件17>
    <零件18>0</零件18>
    <零件19>0</零件19>
    <零件20>0</零件20>
    <零件21>0</零件21>
    <零件22>0</零件22>
    <零件23>0</零件23>
    <零件24>0</零件24>
    <零件25>0</零件25>
    <零件26>0</零件26>
    <零件27>0</零件27>
    <零件28>0</零件28>
    <零件29>0</零件29>
  </分段压力3>
  <分段压力4>
    <零件0>0</零件0>
    <零件1>0</零件1>
    <零件2>0</零件2>
    <零件3>0</零件3>
    <零件4>0</零件4>
    <零件5>0</零件5>
    <零件6>0</零件6>
    <零件7>0</零件7>
    <零件8>0</零件8>
    <零件9>0</零件9>
    <零件10>0</零件10>
    <零件11>0</零件11>
    <零件12>0</零件12>
    <零件13>0</零件13>
    <零件14>0</零件14>
    <零件15>0</零件15>
    <零件16>0</零件16>
    <零件17>0</零件17>
    <零件18>0</零件18>
    <零件19>0</零件19>
    <零件20>0</零件20>
    <零件21>0</零件21>
    <零件22>0</零件22>
    <零件23>0</零件23>
    <零件24>0</零件24>
    <零件25>0</零件25>
    <零件26>0</零件26>
    <零件27>0</零件27>
    <零件28>0</零件28>
    <零件29>0</零件29>
  </分段压力4>
  <分段压力5>
    <零件0>0</零件0>
    <零件1>0</零件1>
    <零件2>0</零件2>
    <零件3>0</零件3>
    <零件4>0</零件4>
    <零件5>0</零件5>
    <零件6>0</零件6>
    <零件7>0</零件7>
    <零件8>0</零件8>
    <零件9>0</零件9>
    <零件10>0</零件10>
    <零件11>0</零件11>
    <零件12>0</零件12>
    <零件13>0</零件13>
    <零件14>0</零件14>
    <零件15>0</零件15>
    <零件16>0</零件16>
    <零件17>0</零件17>
    <零件18>0</零件18>
    <零件19>0</零件19>
    <零件20>0</零件20>
    <零件21>0</零件21>
    <零件22>0</零件22>
    <零件23>0</零件23>
    <零件24>0</零件24>
    <零件25>0</零件25>
    <零件26>0</零件26>
    <零件27>0</零件27>
    <零件28>0</零件28>
    <零件29>0</零件29>
  </分段压力5>
  <分段压力6>
    <零件0>0</零件0>
    <零件1>0</零件1>
    <零件2>0</零件2>
    <零件3>0</零件3>
    <零件4>0</零件4>
    <零件5>0</零件5>
    <零件6>0</零件6>
    <零件7>0</零件7>
    <零件8>0</零件8>
    <零件9>0</零件9>
    <零件10>0</零件10>
    <零件11>0</零件11>
    <零件12>0</零件12>
    <零件13>0</零件13>
    <零件14>0</零件14>
    <零件15>0</零件15>
    <零件16>0</零件16>
    <零件17>0</零件17>
    <零件18>0</零件18>
    <零件19>0</零件19>
    <零件20>0</零件20>
    <零件21>0</零件21>
    <零件22>0</零件22>
    <零件23>0</零件23>
    <零件24>0</零件24>
    <零件25>0</零件25>
    <零件26>0</零件26>
    <零件27>0</零件27>
    <零件28>0</零件28>
    <零件29>0</零件29>
  </分段压力6>
  <分段压力7>
    <零件0>0</零件0>
    <零件1>0</零件1>
    <零件2>0</零件2>
    <零件3>0</零件3>
    <零件4>0</零件4>
    <零件5>0</零件5>
    <零件6>0</零件6>
    <零件7>0</零件7>
    <零件8>0</零件8>
    <零件9>0</零件9>
    <零件10>0</零件10>
    <零件11>0</零件11>
    <零件12>0</零件12>
    <零件13>0</零件13>
    <零件14>0</零件14>
    <零件15>0</零件15>
    <零件16>0</零件16>
    <零件17>0</零件17>
    <零件18>0</零件18>
    <零件19>0</零件19>
    <零件20>0</零件20>
    <零件21>0</零件21>
    <零件22>0</零件22>
    <零件23>0</零件23>
    <零件24>0</零件24>
    <零件25>0</零件25>
    <零件26>0</零件26>
    <零件27>0</零件27>
    <零件28>0</零件28>
    <零件29>0</零件29>
  </分段压力7>
  <分段压力8>
    <零件0>0</零件0>
    <零件1>0</零件1>
    <零件2>0</零件2>
    <零件3>0</零件3>
    <零件4>0</零件4>
    <零件5>0</零件5>
    <零件6>0</零件6>
    <零件7>0</零件7>
    <零件8>0</零件8>
    <零件9>0</零件9>
    <零件10>0</零件10>
    <零件11>0</零件11>
    <零件12>0</零件12>
    <零件13>0</零件13>
    <零件14>0</零件14>
    <零件15>0</零件15>
    <零件16>0</零件16>
    <零件17>0</零件17>
    <零件18>0</零件18>
    <零件19>0</零件19>
    <零件20>0</零件20>
    <零件21>0</零件21>
    <零件22>0</零件22>
    <零件23>0</零件23>
    <零件24>0</零件24>
    <零件25>0</零件25>
    <零件26>0</零件26>
    <零件27>0</零件27>
    <零件28>0</零件28>
    <零件29>0</零件29>
  </分段压力8>
  <分段压力9>
    <零件0>0</零件0>
    <零件1>0</零件1>
    <零件2>0</零件2>
    <零件3>0</零件3>
    <零件4>0</零件4>
    <零件5>0</零件5>
    <零件6>0</零件6>
    <零件7>0</零件7>
    <零件8>0</零件8>
    <零件9>0</零件9>
    <零件10>0</零件10>
    <零件11>0</零件11>
    <零件12>0</零件12>
    <零件13>0</零件13>
    <零件14>0</零件14>
    <零件15>0</零件15>
    <零件16>0</零件16>
    <零件17>0</零件17>
    <零件18>0</零件18>
    <零件19>0</零件19>
    <零件20>0</零件20>
    <零件21>0</零件21>
    <零件22>0</零件22>
    <零件23>0</零件23>
    <零件24>0</零件24>
    <零件25>0</零件25>
    <零件26>0</零件26>
    <零件27>0</零件27>
    <零件28>0</零件28>
    <零件29>0</零件29>
  </分段压力9>
  <分段时间1>
    <零件0>0</零件0>
    <零件1>0</零件1>
    <零件2>0</零件2>
    <零件3>0</零件3>
    <零件4>0</零件4>
    <零件5>0</零件5>
    <零件6>0</零件6>
    <零件7>0</零件7>
    <零件8>0</零件8>
    <零件9>0</零件9>
    <零件10>0</零件10>
    <零件11>0</零件11>
    <零件12>0</零件12>
    <零件13>0</零件13>
    <零件14>0</零件14>
    <零件15>0</零件15>
    <零件16>0</零件16>
    <零件17>0</零件17>
    <零件18>0</零件18>
    <零件19>0</零件19>
    <零件20>0</零件20>
    <零件21>0</零件21>
    <零件22>0</零件22>
    <零件23>0</零件23>
    <零件24>0</零件24>
    <零件25>0</零件25>
    <零件26>0</零件26>
    <零件27>0</零件27>
    <零件28>0</零件28>
    <零件29>0</零件29>
  </分段时间1>
  <分段时间2>
    <零件0>0</零件0>
    <零件1>0</零件1>
    <零件2>0</零件2>
    <零件3>0</零件3>
    <零件4>0</零件4>
    <零件5>0</零件5>
    <零件6>0</零件6>
    <零件7>0</零件7>
    <零件8>0</零件8>
    <零件9>0</零件9>
    <零件10>0</零件10>
    <零件11>0</零件11>
    <零件12>0</零件12>
    <零件13>0</零件13>
    <零件14>0</零件14>
    <零件15>0</零件15>
    <零件16>0</零件16>
    <零件17>0</零件17>
    <零件18>0</零件18>
    <零件19>0</零件19>
    <零件20>0</零件20>
    <零件21>0</零件21>
    <零件22>0</零件22>
    <零件23>0</零件23>
    <零件24>0</零件24>
    <零件25>0</零件25>
    <零件26>0</零件26>
    <零件27>0</零件27>
    <零件28>0</零件28>
    <零件29>0</零件29>
  </分段时间2>
  <分段时间3>
    <零件0>0</零件0>
    <零件1>0</零件1>
    <零件2>0</零件2>
    <零件3>0</零件3>
    <零件4>0</零件4>
    <零件5>0</零件5>
    <零件6>0</零件6>
    <零件7>0</零件7>
    <零件8>0</零件8>
    <零件9>0</零件9>
    <零件10>0</零件10>
    <零件11>0</零件11>
    <零件12>0</零件12>
    <零件13>0</零件13>
    <零件14>0</零件14>
    <零件15>0</零件15>
    <零件16>0</零件16>
    <零件17>0</零件17>
    <零件18>0</零件18>
    <零件19>0</零件19>
    <零件20>0</零件20>
    <零件21>0</零件21>
    <零件22>0</零件22>
    <零件23>0</零件23>
    <零件24>0</零件24>
    <零件25>0</零件25>
    <零件26>0</零件26>
    <零件27>0</零件27>
    <零件28>0</零件28>
    <零件29>0</零件29>
  </分段时间3>
  <分段时间4>
    <零件0>0</零件0>
    <零件1>0</零件1>
    <零件2>0</零件2>
    <零件3>0</零件3>
    <零件4>0</零件4>
    <零件5>0</零件5>
    <零件6>0</零件6>
    <零件7>0</零件7>
    <零件8>0</零件8>
    <零件9>0</零件9>
    <零件10>0</零件10>
    <零件11>0</零件11>
    <零件12>0</零件12>
    <零件13>0</零件13>
    <零件14>0</零件14>
    <零件15>0</零件15>
    <零件16>0</零件16>
    <零件17>0</零件17>
    <零件18>0</零件18>
    <零件19>0</零件19>
    <零件20>0</零件20>
    <零件21>0</零件21>
    <零件22>0</零件22>
    <零件23>0</零件23>
    <零件24>0</零件24>
    <零件25>0</零件25>
    <零件26>0</零件26>
    <零件27>0</零件27>
    <零件28>0</零件28>
    <零件29>0</零件29>
  </分段时间4>
  <分段时间5>
    <零件0>0</零件0>
    <零件1>0</零件1>
    <零件2>0</零件2>
    <零件3>0</零件3>
    <零件4>0</零件4>
    <零件5>0</零件5>
    <零件6>0</零件6>
    <零件7>0</零件7>
    <零件8>0</零件8>
    <零件9>0</零件9>
    <零件10>0</零件10>
    <零件11>0</零件11>
    <零件12>0</零件12>
    <零件13>0</零件13>
    <零件14>0</零件14>
    <零件15>0</零件15>
    <零件16>0</零件16>
    <零件17>0</零件17>
    <零件18>0</零件18>
    <零件19>0</零件19>
    <零件20>0</零件20>
    <零件21>0</零件21>
    <零件22>0</零件22>
    <零件23>0</零件23>
    <零件24>0</零件24>
    <零件25>0</零件25>
    <零件26>0</零件26>
    <零件27>0</零件27>
    <零件28>0</零件28>
    <零件29>0</零件29>
  </分段时间5>
  <分段时间6>
    <零件0>0</零件0>
    <零件1>0</零件1>
    <零件2>0</零件2>
    <零件3>0</零件3>
    <零件4>0</零件4>
    <零件5>0</零件5>
    <零件6>0</零件6>
    <零件7>0</零件7>
    <零件8>0</零件8>
    <零件9>0</零件9>
    <零件10>0</零件10>
    <零件11>0</零件11>
    <零件12>0</零件12>
    <零件13>0</零件13>
    <零件14>0</零件14>
    <零件15>0</零件15>
    <零件16>0</零件16>
    <零件17>0</零件17>
    <零件18>0</零件18>
    <零件19>0</零件19>
    <零件20>0</零件20>
    <零件21>0</零件21>
    <零件22>0</零件22>
    <零件23>0</零件23>
    <零件24>0</零件24>
    <零件25>0</零件25>
    <零件26>0</零件26>
    <零件27>0</零件27>
    <零件28>0</零件28>
    <零件29>0</零件29>
  </分段时间6>
  <分段时间7>
    <零件0>0</零件0>
    <零件1>0</零件1>
    <零件2>0</零件2>
    <零件3>0</零件3>
    <零件4>0</零件4>
    <零件5>0</零件5>
    <零件6>0</零件6>
    <零件7>0</零件7>
    <零件8>0</零件8>
    <零件9>0</零件9>
    <零件10>0</零件10>
    <零件11>0</零件11>
    <零件12>0</零件12>
    <零件13>0</零件13>
    <零件14>0</零件14>
    <零件15>0</零件15>
    <零件16>0</零件16>
    <零件17>0</零件17>
    <零件18>0</零件18>
    <零件19>0</零件19>
    <零件20>0</零件20>
    <零件21>0</零件21>
    <零件22>0</零件22>
    <零件23>0</零件23>
    <零件24>0</零件24>
    <零件25>0</零件25>
    <零件26>0</零件26>
    <零件27>0</零件27>
    <零件28>0</零件28>
    <零件29>0</零件29>
  </分段时间7>
  <分段时间8>
    <零件0>0</零件0>
    <零件1>0</零件1>
    <零件2>0</零件2>
    <零件3>0</零件3>
    <零件4>0</零件4>
    <零件5>0</零件5>
    <零件6>0</零件6>
    <零件7>0</零件7>
    <零件8>0</零件8>
    <零件9>0</零件9>
    <零件10>0</零件10>
    <零件11>0</零件11>
    <零件12>0</零件12>
    <零件13>0</零件13>
    <零件14>0</零件14>
    <零件15>0</零件15>
    <零件16>0</零件16>
    <零件17>0</零件17>
    <零件18>0</零件18>
    <零件19>0</零件19>
    <零件20>0</零件20>
    <零件21>0</零件21>
    <零件22>0</零件22>
    <零件23>0</零件23>
    <零件24>0</零件24>
    <零件25>0</零件25>
    <零件26>0</零件26>
    <零件27>0</零件27>
    <零件28>0</零件28>
    <零件29>0</零件29>
  </分段时间8>
  <分段时间9>
    <零件0>0</零件0>
    <零件1>0</零件1>
    <零件2>0</零件2>
    <零件3>0</零件3>
    <零件4>0</零件4>
    <零件5>0</零件5>
    <零件6>0</零件6>
    <零件7>0</零件7>
    <零件8>0</零件8>
    <零件9>0</零件9>
    <零件10>0</零件10>
    <零件11>0</零件11>
    <零件12>0</零件12>
    <零件13>0</零件13>
    <零件14>0</零件14>
    <零件15>0</零件15>
    <零件16>0</零件16>
    <零件17>0</零件17>
    <零件18>0</零件18>
    <零件19>0</零件19>
    <零件20>0</零件20>
    <零件21>0</零件21>
    <零件22>0</零件22>
    <零件23>0</零件23>
    <零件24>0</零件24>
    <零件25>0</零件25>
    <零件26>0</零件26>
    <零件27>0</零件27>
    <零件28>0</零件28>
    <零件29>0</零件29>
  </分段时间9>
  <调节使能>
    <零件0>false</零件0>
    <零件1>false</零件1>
    <零件2>false</零件2>
    <零件3>false</零件3>
    <零件4>false</零件4>
    <零件5>false</零件5>
    <零件6>false</零件6>
    <零件7>false</零件7>
    <零件8>false</零件8>
    <零件9>false</零件9>
    <零件10>false</零件10>
    <零件11>false</零件11>
    <零件12>false</零件12>
    <零件13>false</零件13>
    <零件14>false</零件14>
    <零件15>false</零件15>
    <零件16>false</零件16>
    <零件17>false</零件17>
    <零件18>false</零件18>
    <零件19>false</零件19>
    <零件20>false</零件20>
    <零件21>false</零件21>
    <零件22>false</零件22>
    <零件23>false</零件23>
    <零件24>false</零件24>
    <零件25>false</零件25>
    <零件26>false</零件26>
    <零件27>false</零件27>
    <零件28>false</零件28>
    <零件29>false</零件29>
  </调节使能>
  <初始力值>
    <零件0>0</零件0>
    <零件1>0</零件1>
    <零件2>0</零件2>
    <零件3>0</零件3>
    <零件4>0</零件4>
    <零件5>0</零件5>
    <零件6>0</零件6>
    <零件7>0</零件7>
    <零件8>0</零件8>
    <零件9>0</零件9>
    <零件10>0</零件10>
    <零件11>0</零件11>
    <零件12>0</零件12>
    <零件13>0</零件13>
    <零件14>0</零件14>
    <零件15>0</零件15>
    <零件16>0</零件16>
    <零件17>0</零件17>
    <零件18>0</零件18>
    <零件19>0</零件19>
    <零件20>0</零件20>
    <零件21>0</零件21>
    <零件22>0</零件22>
    <零件23>0</零件23>
    <零件24>0</零件24>
    <零件25>0</零件25>
    <零件26>0</零件26>
    <零件27>0</零件27>
    <零件28>0</零件28>
    <零件29>0</零件29>
  </初始力值>
  <回调距离>
    <零件0>0</零件0>
    <零件1>0</零件1>
    <零件2>0</零件2>
    <零件3>0</零件3>
    <零件4>0</零件4>
    <零件5>0</零件5>
    <零件6>0</零件6>
    <零件7>0</零件7>
    <零件8>0</零件8>
    <零件9>0</零件9>
    <零件10>0</零件10>
    <零件11>0</零件11>
    <零件12>0</零件12>
    <零件13>0</零件13>
    <零件14>0</零件14>
    <零件15>0</零件15>
    <零件16>0</零件16>
    <零件17>0</零件17>
    <零件18>0</零件18>
    <零件19>0</零件19>
    <零件20>0</零件20>
    <零件21>0</零件21>
    <零件22>0</零件22>
    <零件23>0</零件23>
    <零件24>0</零件24>
    <零件25>0</零件25>
    <零件26>0</零件26>
    <零件27>0</零件27>
    <零件28>0</零件28>
    <零件29>0</零件29>
  </回调距离>
  <夹具补正_X>
    <夹具0>0</夹具0>
    <夹具1>0</夹具1>
    <夹具2>0</夹具2>
    <夹具3>0</夹具3>
    <夹具4>0</夹具4>
    <夹具5>0</夹具5>
    <夹具6>0</夹具6>
    <夹具7>0</夹具7>
    <夹具8>0</夹具8>
    <夹具9>0</夹具9>
    <夹具10>0</夹具10>
    <夹具11>0</夹具11>
    <夹具12>0</夹具12>
    <夹具13>0</夹具13>
    <夹具14>0</夹具14>
    <夹具15>0</夹具15>
    <夹具16>0</夹具16>
    <夹具17>0</夹具17>
    <夹具18>0</夹具18>
    <夹具19>0</夹具19>
  </夹具补正_X>
  <夹具补正_YY>
    <夹具0>0</夹具0>
    <夹具1>0</夹具1>
    <夹具2>0</夹具2>
    <夹具3>0</夹具3>
    <夹具4>0</夹具4>
    <夹具5>0</夹具5>
    <夹具6>0</夹具6>
    <夹具7>0</夹具7>
    <夹具8>0</夹具8>
    <夹具9>0</夹具9>
    <夹具10>0</夹具10>
    <夹具11>0</夹具11>
    <夹具12>0</夹具12>
    <夹具13>0</夹具13>
    <夹具14>0</夹具14>
    <夹具15>0</夹具15>
    <夹具16>0</夹具16>
    <夹具17>0</夹具17>
    <夹具18>0</夹具18>
    <夹具19>0</夹具19>
  </夹具补正_YY>
  <视觉工具>
    <工具0>null</工具0>
    <工具1>null</工具1>
    <工具2>null</工具2>
    <工具3>null</工具3>
    <工具4>null</工具4>
    <工具5>null</工具5>
    <工具6>null</工具6>
    <工具7>null</工具7>
    <工具8>null</工具8>
    <工具9>null</工具9>
  </视觉工具>
  <工具路径>
    <工具0>null</工具0>
    <工具1>null</工具1>
    <工具2>null</工具2>
    <工具3>null</工具3>
    <工具4>null</工具4>
    <工具5>null</工具5>
    <工具6>null</工具6>
    <工具7>null</工具7>
    <工具8>null</工具8>
    <工具9>null</工具9>
  </工具路径>
</PARAMETER>